aula24maio/Dataflow.v
module ULA (b, a, sinal, soma, flag);

input signed [63:0] b, a; 
input [31:0] sinal; // Vem da IR
output signed [63:0] soma;
wire flagBEQ, flagBLT, flagBLTU;
output flag;
wire is_negative;

// Como nao temos uma UC para fazer o controle da ULA, a ULA recebe a palavra de 32 bits e analisa o opcode
// e funct7 (para diferenciar ADD e SUB) e faz subtração ou adição dependendo do que foi lido
// O sinal(instrução por enquanto) vem do IR

wire unsigned [63:0] au, bu;
wire unsigned [63:0] soma_;


assign au = a[63:0];
assign bu = b[63:0];
assign {is_negative, soma_} = au - bu; // Se der overflow, eh negativo e portanto a < b
// assign b_ = ~b + 1; // Transforma o que foi recebido para ser interpretado como unsigned (BLTU e BGEU)

// reg agora vai ter unsigned p a e p b, em vez do padrao ser unsigned

assign soma = (sinal[6:0] == 7'b0000011) ? (a + b): // load
                        (sinal[6:0] == 7'b0100011) ? (a + b): // store
                        (sinal[6:0] == 7'b0110011 && sinal[31:25] == 0 ) ? (a + b): // add - pega opcode e func7 p verificar se soma mesmo
                        (sinal[6:0] == 7'b0010011) ? (a + b): // addi
                        // (sinal[6:0] == 7'b1100011 && sinal[14:12]== 3'b110) ? (au + b_): // BLTU, analisamos o funct3
                        // (sinal[6:0] == 7'b1100011 && sinal[14:12]== 3'b111) ? (au + b_): // BGEU
                                                                                (a - b); // as outras (sub, por exemplo, que tem opcode igual ao add, mas funct7 diferente)

// assign soma_u = (sinal[6:0] == 7'b1100011 && sinal[14:12]== 3'b110) ? (au - bu): // BLTU, analisamos o funct3
//                 (sinal[6:0] == 7'b1100011 && sinal[14:12]== 3'b111) ? (au - bu): // BGEU, analisamoso funct3
//                                                                        (au+bu);

assign flagBEQ = (soma == 0) ? 1:
                               0;
assign flagBLT = (soma < 0) ? 1:
                              0;
assign flagBLTU = (is_negative == 1) ? 1:
                                    0;

 
// always@(a or b)
//     begin
//         if(sinal[6:0] == 7'b1100011 )
//             case(sinal[14:12])
//                 3'b000 : flag <= flagBEQ;
//                 3'b001 : flag <= !flagBEQ;
//                 3'b100 : flag <= flagBLT;
//                 3'b101 : flag <= !flagBLT;
//                 3'b110 : flag <= flagBLT;
//                 3'b111 : flag <= !flagBLT;
//                 default : flag <= 0;
//             endcase
//         else
//             flag <= 0;


//     end

assign flag = (sinal[6:0] == 7'b0000011) ? 0: // load
             (sinal[6:0] == 7'b0100011) ? 0: // store
             (sinal[6:0] == 7'b0110011) ? 0: // add
             (sinal[6:0] == 7'b0010011) ? 0: // addi
             (sinal[6:0] == 7'b1100011 && sinal[14:12] == 3'b000) ? flagBEQ: // BEQ
             (sinal[6:0] == 7'b1100011 && sinal[14:12] == 3'b001) ? !flagBEQ: // BNE
             (sinal[6:0] == 7'b1100011 && sinal[14:12] == 3'b100) ? flagBLT: // BLT
             (sinal[6:0] == 7'b1100011 && sinal[14:12] == 3'b101) ? !flagBLT: // BGE
             (sinal[6:0] == 7'b1100011 && sinal[14:12] == 3'b110) ? flagBLTU: // BLTU
             (sinal[6:0] == 7'b1100011 && sinal[14:12] == 3'b111) ? (!flagBLTU): // BGEU
                                                                            0;

// always@(flagBEQ) begin
//     $display("Flag BEQ:  %d",flagBEQ);
//     $finish;
// end
    
     
endmodule

module somador_four(dout_pc, soma);

input [31:0] dout_pc;
output [31:0] soma;

assign soma = {dout_pc<<2} + 4; // Shift left, pois o PC está em unidade de instrução e não de 4 em 4

endmodule

module somador_imm(dout_pc, imm, soma);

input [31:0] dout_pc;
input [63:0] imm;
output [31:0] soma;

assign soma = {dout_pc<<2} + imm[31:0]; // Shift left, pois o PC está em unidade de instrução e não de 4 em 4

endmodule


module memoria(ads, we, din, dout);
  
input [63:0] ads; // Perguntar para os prof se o endereço da memoria é de 5 ou 64 bits (como sai do somador, a saída padrão é de 64 bits).
input we;
input signed [63:0] din;
output signed [63:0] dout;
reg signed [63:0] registradores [31:0]; // Registradores

initial begin
   
    registradores[0] = 45;
    registradores[1] = 11;
    
end

  // Read operation
  assign dout = (we) ? din : registradores[ads];
  
  // Write operation
  always @(posedge we)
    registradores[ads] <= din;

endmodule

module memoria_ins(ads, dout, rs1, rs2, rd, opcode, we);
  
input [31:0] ads; // Program counter (PC) in RISC-V is 32 bits long (can addres 2³² instructions)
input we;
output [31:0] dout;
output [4:0] rs1;
output [4:0] rd;
output [4:0] rs2;
output [6:0] opcode;


    // add: 0110011 (funct7 = 0000000, funct3 = 000)
    // sub: 0110011 (funct7 = 0100000, funct3 = 000)
    // addi: 0010011 (funct3 = 000)
    // beq: 1100011 (funct3 = 000)
    // bne: 1100011 (funct3 = 001)
    // blt: 1100011 (funct3 = 100)
    // bge: 1100011 (funct3 = 101)
    // bltu: 1100011 (funct3 = 110)
    // bgeu: 1100011 (funct3 = 111)
    // load (e.g., lw, lh, lb): 0000011
    // store (e.g., sw, sh, sb): 0100011

reg signed [31:0] registradores [31:0]; // Registradores

initial begin


   // --------Palavras de instrução --------------------------------------------------
   // O imediato nas branch instructions podem ser colocadas em "unidade" de instrução 
   // Por exemplo, para ir para duas instruções para frente, colocamos no imediato "2"
   // Depois do sign extend do imediato, fazemos um shift left 2, multiplicando por 4
   // Ou seja, indo do registrador[i] para o registrador [i+8], o que seria, justamente, duas instruções para frente

    // registradores[0] = 32'b00000000010100011011000010000011; //LOAD no x1 do que tem no x2 #3 (endereço = 5) da memoria
    // registradores[1] = 32'b00000000001000010011001000100011; // STORE no x2 #4 do que tem no x2 do banco de registradores
    // registradores[2] = 32'b00000000001000001000000110110011; // ADD de x1 e x2 e registra em x3 (tudo no banco de registradores)
    // registradores[3] = 32'b01000000001000001000001000110011; //SUB de x1 e x2 e registra em x4 (tudo no banco de registradores)
    // registradores[4] = 32'b00000000001100001000001010010011; // ADDI de x1 e 3 e registra em x5 (tudo no banco de registradores)
    // // registradores[5] = 32'b00000000000100000100000101100011; // BEQ, compara x1 e x2, caso TRUE, vai para BNE
    // registradores[6] = 32'b00000000001000001000000001100011; // BLT
    // registradores[7] = 32'b00000000000100000100100001100011; // BNE, compara x1 e x2, caso TRUE, vai para BLTU
    registradores[0] = {1'b0, 6'b000000, 5'b00001, 5'b00010, 3'b000, 4'b0010, 1'b0, 7'b1100011}; // BEQ, compara x1 e x2, caso TRUE vai para BNE
    registradores[1] = {1'b0, 6'b000000, 5'b00001, 5'b00011, 3'b100, 4'b0010, 1'b0, 7'b1100011}; // BLT, compara x1 e x3, caso TRUE, vai para BGE
    registradores[2] = {1'b1, 6'b111111, 5'b00001, 5'b00011, 3'b001, 4'b1111, 1'b1, 7'b1100011}; // BNE, compara x1 e x3, caso TRUE, vai para BLT
    registradores[3] = {1'b1, 6'b111111, 5'b00001, 5'b00011, 3'b101, 4'b1111, 1'b1, 7'b1100011}; // BGE, compara x1 e x3, caso FALSE, vai para o próximo (BLTU)
    registradores[4] = {1'b1, 6'b000000, 5'b00100, 5'b00101, 3'b110, 4'b0010, 1'b0, 7'b1100011}; // BLTU, compara x5 e x4, caso TRUE, vai para BGEU
    registradores[6] = {1'b0, 6'b000000, 5'b00100, 5'b00101, 3'b111, 4'b0010, 1'b0, 7'b1100011}; // BGEU, compara x5 e x4, caso TRUE, vai para ...

    // Nao existe SUBI, como podemos apenar colocar o imediato do ADDI (sempre lido como complemento de 2) como um numero negativo

    
end


assign dout = (we) ? registradores[0] : registradores[ads];
assign rd = (we) ? registradores[0][11:7] : registradores[ads][11:7]; // Write addres for the registers in LOAD, ADD, SUB, ADDI instructions
assign rs1 = (we) ? registradores[0][19:15] : registradores[ads][19:15]; // Read addres for the registers in LOAD, ADD, SUB, STORE, ADDI, BNE, ... instructions
assign rs2 = (we) ? registradores[0][24:20] : registradores[ads][24:20]; // Another read addres for the registers in ADD, SUB, STORE, BNE, BEQ, ... instructions
assign opcode = (we) ? registradores[0][6:0] : registradores[ads][6:0]; // Opcode in all instructions


// Read operations
// assign dout =  registradores[ads];
// assign rd = registradores[ads][11:7]; // Write addres for the registers in LOAD, ADD, SUB, ADDI instructions
// assign rs1 = registradores[ads][19:15]; // Read addres for the registers in LOAD, ADD, SUB, STORE, ADDI, BNE, ... instructions
// assign rs2 = registradores[ads][24:20]; // Another read addres for the registers in ADD, SUB, STORE, BNE, BEQ, ... instructions
// assign opcode = registradores[ads][6:0]; // Opcode in all instructions


endmodule

module PC(clock, r_enable, data_in, data_out);

input             clock;
input             r_enable;
input      [31:0] data_in;
output reg [31:0] data_out;

initial begin
    data_out <=0;

end

always @(posedge clock)
begin
    if(r_enable)
        data_out <= data_in[7:2]; 
end

endmodule


module IR(clock, r_enable, data_in, data_out);

input             clock;
input             r_enable;
input      [31:0] data_in;
output reg [31:0] data_out;
output reg [6:0] opcode;

always @(posedge clock)
begin
    if(r_enable) begin
        data_out <= data_in[31:0]; // Sai a palavra de 32 bits
    end

end

endmodule

module imm_generator(
    palavra, // Vem da IR
    opcode, // Vem da Memoria de Instrução
    imm
);

input signed [31:0] palavra;
input [6:0] opcode;
output signed [63:0] imm;

wire signed [11:0] imm_field;

  // Select the appropriate bits for the immediate field based on the opcode (in case we dont need immediate, it takes the default field)
  assign imm_field = (opcode == 7'b0000011) ? palavra[31:20] : // LOAD
                     (opcode == 7'b0100011) ? {palavra[31:25],palavra[11:7]} : // STORE
                     (opcode == 7'b1100011) ? {palavra[31],palavra[7], palavra[30:25],palavra[11:8]}  : // BRANCH INSTRUCTIONS (BEQ, BNE, etc)
                     (opcode == 7'b0010011) ? palavra[31:20] : // ADDI
                                              palavra[31:20]; // ADD, SUB -> don't care

  // Sign-extend the immediate field to 64 bits and shifts left by 2 if it is a branch instruction
  assign imm = (opcode == 7'b1100011) ? {{50{imm_field[11]}}, imm_field} << 2:
                                        {{64{imm_field[11]}}, imm_field}; // se não for branch instruction, apenas faz o signal extend

endmodule



module registrador (clk, din, we, Rw, Ra, Rb, doutA, doutB);
    input clk;             // Clock do sistema
    input signed [63:0] din; // Dados de entrada  
    input we;          // Sinal de carregamento de dados
    output reg signed [64-1:0] doutA; // Dado de saída
    output reg signed [64-1:0]  doutB; // Dado de saída
    input [4:0] Rw; // Vai vir da memoria de instrução
    input [4:0] Ra; // Vai vir da memoria de instrução
    input [4:0] Rb; // Vai vir da memoria de instrução

    reg signed [63:0] registradores [31:0]; //Registradores

    initial begin
        
        registradores[0] = 1;
        registradores[1] = 1;
        registradores[2] = 1;
        registradores[3] = 0;
        registradores[4] = 64'b1111111111111111111111111111111111111111111111111111111111111111;
        // registradores[5] = 64'b1111111111111111111111111111111111111111111111111111111111111110;;
        registradores[5] = 64'b0000000000000000000000000000000000000000000000000000000000000001;

    end

    // Temos clock em registradores, por isso vamos usar o always

    always @(posedge clk) begin

        // $display("Registrador do banco onde ocorre o primeiro LOAD:", registradores[1]); 
        // $display("Registrador do banco onde ocorre o primeiro ADD :", registradores[3]); 
        // $display("Registrador do banco onde ocorre o primeiro SUB :", registradores[4]); 
        // $display("Registrador do banco onde ocorre o ADDI :", registradores[2]); 
        // $display("Registrador do banco onde ocorre o SUBI :", registradores[7]); 
        
        

        if (we) begin // Se o sinal de carregamento de dados estiver ativo
            registradores[Rw] <= din; // Carrega os dados de entrada no registrador

        end
        begin
            doutA <= registradores[Ra]; // Lê os dados do registrador 
            doutB <= registradores[Rb]; // Lê os dados do registrador 
        end
        // $display(doutA);
        // $finish;
        

    end

    

endmodule

module Mux1 (imm , doutB, sinalMux, S1 );

input signed [63:0] doutB;
input signed [63:0] imm; // Imediato extendido
output signed [63:0] S1;
input sinalMux;


assign S1 = (sinalMux == 1'b0) ? imm: doutB;
            
endmodule


module Mux2 (dout, soma ,sinalMux, S2);

input signed [63:0] dout, soma;
output signed [63:0] S2;
input sinalMux;


assign S2 = (sinalMux == 1'b0) ? (dout):(soma);
            
endmodule

module Mux3 (imm_some, four_some, flag, S3);

input [31:0] imm_some; // Vem do somador_imm
input [31:0] four_some; // Vem do somador_four
output [31:0] S3; // Vai para o PC
input flag; // Vem da ULA


assign S3 = (flag == 1'b0) ? (four_some):(imm_some);
            
endmodule

aula24maio/testbench.v
`timescale 1ns/1ns

module testbench;

    // Inputs
    reg clock_tb;
    reg sinal_tb;
    wire signed [63:0] res_tb;
    wire [63:0] doutMem_tb;
    reg weReg_tb;
    wire [4:0] Rw_tb;
    wire [4:0] Ra_tb, Rb_tb;
    wire [6:0] opcode_tb;
    wire signed [63:0] doutA_tb;
    wire signed [63:0] doutB_tb;
    wire signed [63:0] S1_tb;
    wire signed [63:0] S2_tb;
    reg weMem_tb, wePC_tb, weIR_tb, weMemIns_tb;
    reg sinalMux1_tb;
    reg sinalMux2_tb;
    wire [31:0] C_tb;
    wire [31:0] PC_tb;
    wire [31:0] IR_tb;
    wire [31:0] doutIR_tb;
    wire flag_tb;
    wire signed [63:0] imm_tb;
    wire [31:0] somafour_tb, somaimm_tb;

    ULA uut (
        .a(doutA_tb), 
        .b(S1_tb), 
        .soma(res_tb),
        .sinal(IR_tb),
        .flag(flag_tb)
    );

    registrador utt (

        .clk(clock_tb),
        .din(S2_tb),
        .we(weReg_tb),
        .Rw(Rw_tb),
        .Ra(Ra_tb),
        .Rb(Rb_tb),
        .doutA(doutA_tb),
        .doutB(doutB_tb)
    );

    memoria utu (

        .ads(res_tb),
        .we(weMem_tb),
        .din(doutB_tb),
        .dout(doutMem_tb)
    );

    Mux1 utv (
        .imm(imm_tb),
        .doutB(doutB_tb),
        .sinalMux(sinalMux1_tb),
        .S1(S1_tb)
    );

    Mux2 uvv (
        .dout(doutMem_tb),
        .soma(res_tb),
        .sinalMux(sinalMux2_tb),
        .S2(S2_tb)
    );
    
    memoria_ins utH (

        .ads(PC_tb),
        .we(weMemIns_tb),
        .dout(IR_tb),
        .rs1(Ra_tb),
        .rs2(Rb_tb),
        .rd(Rw_tb),
        .opcode(opcode_tb)
    );

    PC uhh(
        .clock(clock_tb),
        .r_enable(wePC_tb),
        .data_in(C_tb),
        .data_out(PC_tb)
    );

    IR huu (
        .clock(clock_tb),
        .r_enable(weIR_tb),
        .data_in(IR_tb),
        .data_out(doutIR_tb)

    );

    imm_generator hii (
        .palavra(doutIR_tb),
        .opcode(opcode_tb),
        .imm(imm_tb)

    );

    somador_four itt(
        .dout_pc(PC_tb),
        .soma(somafour_tb)

    );

    somador_imm its (
        .dout_pc(PC_tb),
        .imm(imm_tb),
        .soma(somaimm_tb)
    );

    Mux3 ihs (
        .four_some(somafour_tb),
        .imm_some(somaimm_tb),
        .flag(flag_tb),
        .S3(C_tb)
    );


    initial $dumpfile("testbench.vcd");
    initial $dumpvars(0, testbench);

    initial 
    begin
        
        //*******************************Abaixo é a simulação: ********************************************************************

        //************** Começa BEQ ******************************************************************
        // Primeiro, vamos comparar o que tem no registrador 1 e 2. Se forem iguais,a flag indica TRUE
        // e pulamos para a instrução BLT. Vamos testar:

        sinalMux1_tb = 1; // Seleciona doutB
        clock_tb = 0; // Inicializa o clock
        sinalMux2_tb = 0; // Don't care se o que vai para o Din do Banco de Registradores é o resultado da soma ou a saída da memória
        weIR_tb = 1; // Para registrar a instrução atual
        weMem_tb = 0; // Não vamos escrever nada na memória
        weMemIns_tb = 1;
        weReg_tb = 0; // Não vamos escrever nada no banco de registradores
        wePC_tb = 0; // Como inicializamos uma instrucao, não ativamos o we do PC

        #10
        #10 // Espera dois clocks; Um para a soma e outro para o registrador

        $display("Flag BEQ entre x1 e x2: %d", flag_tb); // Como é verdadeiro (1=1), a flag está como 1. Logo, somamos o imediato (2) ao PC (5).

        //************** Começa BNE *******************************************************
        wePC_tb  = 1; // Vamos mudar a instrução para BNE
        weMemIns_tb =0;
        weIR_tb = 1; // Para registrar a instrução atual
        sinalMux1_tb = 1; // Seleciona doutB
        sinalMux2_tb = 0; // Don't care se o que vai para o Din do Banco de Registradores é o resultado da soma ou a saída da memória
        weMem_tb = 0; // Não vamos escrever nada na memória
        weReg_tb = 0; // Não vamos escrever nada no banco de registradores

        #10
        #10 // Se dermos display da flag aqui, veremos que ela vem para 0 em um dado momento. Analisando o GTK Wave, percebe-se que isso ocorre
            // em razão da mudança de instrução momentaneamente. Como o resultado da soma ainda não foi dado, ele dá a flag em função do último resultado.
        wePC_tb  = 0; // Vamos mudar a instrução para BNE

        #10
        #10

        $display("Flag BNE entre x1 e x3: %d", flag_tb); // Veja que a flag está como 1, pois x1 e x3 são diferentes.

        //************** Começa BLT *******************************************************

        wePC_tb  = 1; // Vamos mudar a instrução para BLT
        weMemIns_tb =0;
        weIR_tb = 1; // Para registrar a instrução atual
        sinalMux1_tb = 1; // Seleciona doutB
        sinalMux2_tb = 0; // Don't care se o que vai para o Din do Banco de Registradores é o resultado da soma ou a saída da memória
        weMem_tb = 0; // Não vamos escrever nada na memória
        weReg_tb = 0; // Não vamos escrever nada no banco de registradores
        
        #10
        #10
        wePC_tb  = 0; 
        #10
        #10
        $display("Flag BLT entre x1 e x3: %d", flag_tb); // Veja que a flag está como 1, pois x1 <x3.

        //************** Começa BGE *******************************************************

        wePC_tb  = 1; // Vamos mudar a instrução para BGE
        weMemIns_tb =0;
        weIR_tb = 1; // Para registrar a instrução atual
        sinalMux1_tb = 1; // Seleciona doutB
        sinalMux2_tb = 0; // Don't care se o que vai para o Din do Banco de Registradores é o resultado da soma ou a saída da memória
        weMem_tb = 0; // Não vamos escrever nada na memória
        weReg_tb = 0; // Não vamos escrever nada no banco de registradores

        #10
        #10
        wePC_tb  = 0; 
        #10
        #10
        $display("Flag BGE entre x1 e x3: %d", flag_tb); // Veja que a flag está como 0, pois x1 <x3.
        
        //************** Começa BLTU *******************************************************

        wePC_tb  = 1; // Vamos mudar a instrução para BLTU
        weMemIns_tb =0;
        weIR_tb = 1; // Para registrar a instrução atual
        sinalMux1_tb = 1; // Seleciona doutB
        sinalMux2_tb = 0; // Don't care se o que vai para o Din do Banco de Registradores é o resultado da soma ou a saída da memória
        weMem_tb = 0; // Não vamos escrever nada na memória
        weReg_tb = 0; // Não vamos escrever nada no banco de registradores

        #10
        #10
        wePC_tb  = 0; 
        #10
        #10
        $display("Flag BLTU entre x5 e x4: %d", flag_tb); // Veja que a flag está como 1, pois x5 <x4.
        #10

        //************** Começa BGEU*******************************************************

        wePC_tb  = 1; // Vamos mudar a instrução para BGEU
        weMemIns_tb =0;
        weIR_tb = 1; // Para registrar a instrução atual
        sinalMux1_tb = 1; // Seleciona doutB
        sinalMux2_tb = 0; // Don't care se o que vai para o Din do Banco de Registradores é o resultado da soma ou a saída da memória
        weMem_tb = 0; // Não vamos escrever nada na memória
        weReg_tb = 0; // Não vamos escrever nada no banco de registradores

        #10
        #10
        wePC_tb  = 0; 
        #10
        #10
        $display("Flag BGEU entre x5 e x4: %d", flag_tb); // Veja que a flag está como 0, pois x5 <x4.
        #10


        



       
$finish;

     
    end

        always #10 clock_tb = ~clock_tb;
    
    



endmodule

aula24maio/testbench.vcd
$date
	Tue May 23 23:25:57 2023
$end
$version
	Icarus Verilog
$end
$timescale
	1ns
$end
$scope module testbench $end
$var wire 32 ! somaimm_tb [31:0] $end
$var wire 32 " somafour_tb [31:0] $end
$var wire 64 # res_tb [63:0] $end
$var wire 7 $ opcode_tb [6:0] $end
$var wire 64 % imm_tb [63:0] $end
$var wire 1 & flag_tb $end
$var wire 64 ' doutMem_tb [63:0] $end
$var wire 32 ( doutIR_tb [31:0] $end
$var wire 64 ) doutB_tb [63:0] $end
$var wire 64 * doutA_tb [63:0] $end
$var wire 64 + S2_tb [63:0] $end
$var wire 64 , S1_tb [63:0] $end
$var wire 5 - Rw_tb [4:0] $end
$var wire 5 . Rb_tb [4:0] $end
$var wire 5 / Ra_tb [4:0] $end
$var wire 32 0 PC_tb [31:0] $end
$var wire 32 1 IR_tb [31:0] $end
$var wire 32 2 C_tb [31:0] $end
$var reg 1 3 clock_tb $end
$var reg 1 4 sinalMux1_tb $end
$var reg 1 5 sinalMux2_tb $end
$var reg 1 6 weIR_tb $end
$var reg 1 7 weMemIns_tb $end
$var reg 1 8 weMem_tb $end
$var reg 1 9 wePC_tb $end
$var reg 1 : weReg_tb $end
$scope module hii $end
$var wire 32 ; palavra [31:0] $end
$var wire 7 < opcode [6:0] $end
$var wire 12 = imm_field [11:0] $end
$var wire 64 > imm [63:0] $end
$upscope $end
$scope module huu $end
$var wire 1 3 clock $end
$var wire 1 6 r_enable $end
$var wire 32 ? data_in [31:0] $end
$var reg 32 @ data_out [31:0] $end
$var reg 7 A opcode [6:0] $end
$upscope $end
$scope module ihs $end
$var wire 32 B imm_some [31:0] $end
$var wire 32 C four_some [31:0] $end
$var wire 1 & flag $end
$var wire 32 D S3 [31:0] $end
$upscope $end
$scope module its $end
$var wire 64 E imm [63:0] $end
$var wire 32 F soma [31:0] $end
$var wire 32 G dout_pc [31:0] $end
$upscope $end
$scope module itt $end
$var wire 32 H soma [31:0] $end
$var wire 32 I dout_pc [31:0] $end
$upscope $end
$scope module uhh $end
$var wire 1 3 clock $end
$var wire 32 J data_in [31:0] $end
$var wire 1 9 r_enable $end
$var reg 32 K data_out [31:0] $end
$upscope $end
$scope module utH $end
$var wire 32 L ads [31:0] $end
$var wire 1 7 we $end
$var wire 5 M rs2 [4:0] $end
$var wire 5 N rs1 [4:0] $end
$var wire 5 O rd [4:0] $end
$var wire 7 P opcode [6:0] $end
$var wire 32 Q dout [31:0] $end
$upscope $end
$scope module utt $end
$var wire 5 R Ra [4:0] $end
$var wire 5 S Rb [4:0] $end
$var wire 5 T Rw [4:0] $end
$var wire 1 3 clk $end
$var wire 1 : we $end
$var wire 64 U din [63:0] $end
$var reg 64 V doutA [63:0] $end
$var reg 64 W doutB [63:0] $end
$upscope $end
$scope module utu $end
$var wire 64 X din [63:0] $end
$var wire 1 8 we $end
$var wire 64 Y dout [63:0] $end
$var wire 64 Z ads [63:0] $end
$upscope $end
$scope module utv $end
$var wire 64 [ doutB [63:0] $end
$var wire 64 \ imm [63:0] $end
$var wire 1 4 sinalMux $end
$var wire 64 ] S1 [63:0] $end
$upscope $end
$scope module uut $end
$var wire 64 ^ a [63:0] $end
$var wire 64 _ au [63:0] $end
$var wire 64 ` b [63:0] $end
$var wire 64 a bu [63:0] $end
$var wire 32 b sinal [31:0] $end
$var wire 64 c soma_ [63:0] $end
$var wire 64 d soma [63:0] $end
$var wire 1 e is_negative $end
$var wire 1 f flagBLTU $end
$var wire 1 g flagBLT $end
$var wire 1 h flagBEQ $end
$var wire 1 & flag $end
$upscope $end
$scope module uvv $end
$var wire 64 i dout [63:0] $end
$var wire 1 5 sinalMux $end
$var wire 64 j soma [63:0] $end
$var wire 64 k S2 [63:0] $end
$upscope $end
$upscope $end
$enddefinitions $end
#0
$dumpvars
bx k
bx j
bx i
xh
xg
xf
xe
bx d
bx c
b100010000001001100011 b
bx a
bx `
bx _
bx ^
bx ]
bx00 \
bx [
bx Z
bx Y
bx X
bx W
bx V
bx U
b100 T
b1 S
b10 R
b100010000001001100011 Q
b1100011 P
b100 O
b10 N
b1 M
b0 L
b0 K
bx J
b0 I
b100 H
b0 G
bx F
bx00 E
bx D
b100 C
bx B
bx A
bx @
b100010000001001100011 ?
bx00 >
bx =
b1100011 <
bx ;
0:
09
08
17
16
05
14
03
bx 2
b100010000001001100011 1
b0 0
b10 /
b1 .
b100 -
bx ,
bx +
bx *
bx )
bx (
bx '
x&
bx00 %
b1100011 $
bx #
b100 "
bx !
$end
#10
1&
b1000 2
b1000 D
b1000 J
b1000 !
b1000 B
b1000 F
1h
0g
b101101 +
b101101 U
b101101 k
b1000 %
b1000 >
b1000 E
b1000 \
b101101 '
b101101 Y
b101101 i
b0 #
b0 Z
b0 d
b0 j
0f
b10 =
b0 c
0e
b1 a
b1 ,
b1 ]
b1 `
b1 )
b1 W
b1 X
b1 [
b1 _
b1 *
b1 V
b1 ^
b100010000001001100011 (
b100010000001001100011 ;
b100010000001001100011 @
13
#20
03
07
19
#30
0&
b11111 -
b11111 O
b11111 T
b11 /
b11 N
b11 R
b1100 2
b1100 D
b1100 J
b11111110000100011001111111100011 1
b11111110000100011001111111100011 ?
b11111110000100011001111111100011 Q
b11111110000100011001111111100011 b
b1100 "
b1100 C
b1100 H
b10000 !
b10000 B
b10000 F
b10 0
b10 G
b10 I
b10 K
b10 L
13
#40
03
09
#50
b100 2
b100 D
b100 J
1&
b100 !
b100 B
b100 F
b1111111111111111111111111111111111111111111111111111111111111100 %
b1111111111111111111111111111111111111111111111111111111111111100 >
b1111111111111111111111111111111111111111111111111111111111111100 E
b1111111111111111111111111111111111111111111111111111111111111100 \
0h
1g
bx +
bx U
bx k
bx '
bx Y
bx i
b1111111111111111111111111111111111111111111111111111111111111111 #
b1111111111111111111111111111111111111111111111111111111111111111 Z
b1111111111111111111111111111111111111111111111111111111111111111 d
b1111111111111111111111111111111111111111111111111111111111111111 j
b111111111111 =
1f
b1111111111111111111111111111111111111111111111111111111111111111 c
1e
b0 _
b0 *
b0 V
b0 ^
b11111110000100011001111111100011 (
b11111110000100011001111111100011 ;
b11111110000100011001111111100011 @
13
#60
03
19
#70
b100 -
b100 O
b100 T
b0 2
b0 D
b0 J
b100011100001001100011 1
b100011100001001100011 ?
b100011100001001100011 Q
b100011100001001100011 b
b1000 "
b1000 C
b1000 H
b0 !
b0 B
b0 F
b1 0
b1 G
b1 I
b1 K
b1 L
13
#80
03
09
#90
b1100 2
b1100 D
b1100 J
b1100 !
b1100 B
b1100 F
b1000 %
b1000 >
b1000 E
b1000 \
b10 =
b100011100001001100011 (
b100011100001001100011 ;
b100011100001001100011 @
13
#100
03
19
#110
0&
b11111 -
b11111 O
b11111 T
b10000 2
b10000 D
b10000 J
b11111110000100011101111111100011 1
b11111110000100011101111111100011 ?
b11111110000100011101111111100011 Q
b11111110000100011101111111100011 b
b10000 "
b10000 C
b10000 H
b10100 !
b10100 B
b10100 F
b11 0
b11 G
b11 I
b11 K
b11 L
13
#120
03
09
#130
b1000 !
b1000 B
b1000 F
b1111111111111111111111111111111111111111111111111111111111111100 %
b1111111111111111111111111111111111111111111111111111111111111100 >
b1111111111111111111111111111111111111111111111111111111111111100 E
b1111111111111111111111111111111111111111111111111111111111111100 \
b111111111111 =
b11111110000100011101111111100011 (
b11111110000100011101111111100011 ;
b11111110000100011101111111100011 @
13
#140
03
19
#150
1&
b100 -
b100 O
b100 T
b101 /
b101 N
b101 R
b100 .
b100 M
b100 S
b1100 2
b1100 D
b1100 J
b10000000010000101110001001100011 1
b10000000010000101110001001100011 ?
b10000000010000101110001001100011 Q
b10000000010000101110001001100011 b
b10100 "
b10100 C
b10100 H
b1100 !
b1100 B
b1100 F
b100 0
b100 G
b100 I
b100 K
b100 L
13
#160
03
09
#170
1&
b11111111111111111110000000011000 2
b11111111111111111110000000011000 D
b11111111111111111110000000011000 J
b11111111111111111110000000011000 !
b11111111111111111110000000011000 B
b11111111111111111110000000011000 F
b1111111111111111111111111111111111111111111111111110000000001000 %
b1111111111111111111111111111111111111111111111111110000000001000 >
b1111111111111111111111111111111111111111111111111110000000001000 E
b1111111111111111111111111111111111111111111111111110000000001000 \
0h
0g
bx +
bx U
bx k
bx '
bx Y
bx i
b10 #
b10 Z
b10 d
b10 j
b100000000010 =
1f
b1111111111111111111111111111111111111111111111111111111111111111 a
b1111111111111111111111111111111111111111111111111111111111111111 ,
b1111111111111111111111111111111111111111111111111111111111111111 ]
b1111111111111111111111111111111111111111111111111111111111111111 `
b10 c
1e
b1111111111111111111111111111111111111111111111111111111111111111 )
b1111111111111111111111111111111111111111111111111111111111111111 W
b1111111111111111111111111111111111111111111111111111111111111111 X
b1111111111111111111111111111111111111111111111111111111111111111 [
b1 _
b1 *
b1 V
b1 ^
b10000000010000101110001001100011 (
b10000000010000101110001001100011 ;
b10000000010000101110001001100011 @
13
#180
03
#190
0&
b11100 2
b11100 D
b11100 J
b10000101111001001100011 1
b10000101111001001100011 ?
b10000101111001001100011 Q
b10000101111001001100011 b
b11100 "
b11100 C
b11100 H
b11111111111111111110000000100000 !
b11111111111111111110000000100000 B
b11111111111111111110000000100000 F
b110 0
b110 G
b110 I
b110 K
b110 L
13
19
#200
03
#210
b100000 !
b100000 B
b100000 F
b1000 %
b1000 >
b1000 E
b1000 \
b10 =
b10000101111001001100011 (
b10000101111001001100011 ;
b10000101111001001100011 @
13
09
