aula8demaio/Dataflow.v
module adder (a,b,sinal, soma);

input signed [63:0] a, b;
output signed [63:0] soma;
input sinal;


assign soma = (sinal == 1'b0) ? (a + b):(a-b);
            
endmodule

module memoria(ads, clk, we, din, dout);
  
input [63 :0] ads;
input clk;
input we;
input signed [63:0] din;
output reg signed [63:0] dout;
reg signed [63:0] registradores [31:0]; // Registradores

initial begin
   
    registradores[0] = 45;
    registradores[1] = 11;
    
end

always@(posedge clk) begin

    $display("Registrador da memoria que recebe STORE         :", registradores[3]); 

    if (we)
        begin
          registradores[ads] <= din; // Escreve na memoria
        end
    else 
        begin
            dout <= registradores[ads]; // Lê a memoria
        end
end


endmodule

module memoriaIns(ads, clk, we, din, dout);
  
input [63 :0] ads;
input clk;
input we;
input signed [63:0] din;
output reg signed [63:0] dout;
reg signed [63:0] registradores [31:0]; // Registradores

initial begin
   // Mude aqui os enderecos de cada imediato aqui nos 12 bits mais significativos a partir da metade dos 64bits
    registradores[1] = 64'b0000000000000000000000000000000000000000000000000000000000000000; //LOAD
    registradores[2] = 64'b0000000000000000000000000000000000000000000100000000000000100001; // STORE
    registradores[3] = 64'b0000000000000000000000000000000000000000000000000000000000100001; // ADD
    registradores[4] = 64'b0000000000000000000000000000000000000000000000000000000000100001; //SUB
    registradores[5] = 64'b0000000000000000000000000000000000000000000100000000000000100001; // ADDI
    registradores[6] = 64'b0000000000000000000000000000000000000000001000000000000000100001; //SUBI

    
end

always@(posedge clk) begin


    if (we)
        begin
          registradores[ads] <= din; // Escreve na memoria
        end
    else 
        begin
            dout <= registradores[ads]; // Lê a memoria
        end
end


endmodule


module PC(clock, r_enable, data_in, data_out);

input             clock;
input             r_enable;
input      [63:0] data_in;
output reg [63:0] data_out;

initial begin

end

always @(posedge clock)
begin
    if(r_enable)
        data_out <= data_in;
end

endmodule


module IR(clock, r_enable, data_in, data_out);

input             clock;
input             r_enable;
input      [63:0] data_in;
output reg [31:0] data_out;

always @(posedge clock)
begin
    if(r_enable)
        data_out <= data_in[31:0];
end

endmodule

module registrador (clk, din, we, Rw, Ra, Rb, doutA, doutB);
    input clk;             // Clock do sistema
    input signed [63:0] din; // Dados de entrada  
    input we;          // Sinal de carregamento de dados
    output reg signed [64-1:0] doutA; 
    output reg signed [64-1:0]  doutB; // Dados de saída
    input [63:0] Rw;
    input [63:0] Ra;
    input [63:0] Rb;

    reg signed [63:0] registradores [31:0]; //Registradores

    initial begin
        
        registradores[0] = 1;
        registradores[1] = 1;
        registradores[2] = 3;
        registradores[3] = 0;
        registradores[5] = 2;
        registradores[6] = 36;

    end

    always @(posedge clk) begin

        $display("Registrador do banco onde ocorre o primeiro LOAD:", registradores[1]); 
        
        $display("Registrador do banco onde ocorre o primeiro ADD :", registradores[3]); 
        $display("Registrador do banco onde ocorre o primeiro SUB :", registradores[4]); 
        $display("Registrador do banco onde ocorre o ADDI :", registradores[2]); 
        $display("Registrador do banco onde ocorre o SUBI :", registradores[7]); 
        
        

        if (we) begin // Se o sinal de carregamento de dados estiver ativo
            registradores[Rw] <= din; // Carrega os dados de entrada no registrador
          
    
        end
        begin
            doutA <= registradores[Ra]; // Lê os dados do registrador 
            doutB <= registradores[Rb]; // Lê os dados do registrador 

    end
    end

    

endmodule

module Mux1 (C,Rb,sinalMux,S1 );

input signed [63:0] Rb;
input signed [31:0] C;
output signed [63:0] S1;
input sinalMux;


assign S1 = (sinalMux == 1'b0) ? C[31:20]: Rb;
            
endmodule


module Mux2 (dout, soma ,sinalMux, S2);

input signed [63:0] dout, soma;
output signed [63:0] S2;
input sinalMux;


assign S2 = (sinalMux == 1'b0) ? (dout):(soma);
            
endmodule

aula8demaio/testbench.v
`timescale 1ns/1ns

module testbench;

    // Inputs
    reg clock_tb;
    reg sinal_tb;
    wire signed [63:0] res_tb;
    wire [63:0] doutMem_tb;
    reg weReg_tb;
    reg [63:0] Rw_tb;
    reg [63:0] Ra_tb, Rb_tb;
    wire signed [63:0] doutA_tb;
    wire signed [63:0] doutB_tb;
    wire signed [63:0] S1_tb;
    wire signed [63:0] S2_tb;
    reg weMem_tb, weMemIns_tb, wePC_tb, weIR_tb;
    reg [63:0] dinMemIns_tb;
    reg sinalMux1_tb;
    reg sinalMux2_tb;
    reg signed [63:0] C_tb;
    wire [63:0] PC_tb;
    wire [63:0] IR_tb;
    wire [31:0] doutIR_tb;

    adder uut (
        .a(doutA_tb), 
        .b(S1_tb), 
        .soma(res_tb),
        .sinal(sinal_tb)
    );

    registrador utt (

        .clk(clock_tb),
        .din(S2_tb),
        .we(weReg_tb),
        .Rw(Rw_tb),
        .Ra(Ra_tb),
        .Rb(Rb_tb),
        .doutA(doutA_tb),
        .doutB(doutB_tb)
    );

    memoria utu (

        .clk(clock_tb),
        .ads(res_tb),
        .we(weMem_tb),
        .din(doutB_tb),
        .dout(doutMem_tb)
    );

    Mux1 utv (
        .C(doutIR_tb),
        .Rb(doutB_tb),
        .sinalMux(sinalMux1_tb),
        .S1(S1_tb)
    );

    Mux2 uvv (
        .dout(doutMem_tb),
        .soma(res_tb),
        .sinalMux(sinalMux2_tb),
        .S2(S2_tb)
    );
    
    memoriaIns utH (

        .clk(clock_tb),
        .ads(PC_tb),
        .we(weMemIns_tb),
        .din(dinMemIns_tb),
        .dout(IR_tb)
    );

    PC uhh(
        .clock(clock_tb),
        .r_enable(wePC_tb),
        .data_in(C_tb),
        .data_out(PC_tb)
    );

    IR huu (
        .clock(clock_tb),
        .r_enable(weIR_tb),
        .data_in(IR_tb),
        .data_out(doutIR_tb)

    );


    initial $dumpfile("testbench.vcd");
    initial $dumpvars(0, testbench);

    initial 
    begin
         //Para simular, precisa-se dar o sinal de clock(que será 0 ou 1), também o sinal do somador(0 se for soma ou 1 se for subtração),
        //Ainda, deve-se fornecer o b_tb que é endereço que será somado com zero(a_tb), e que será o endereço da memória. Por fim, também
        //é necessário fornecer o rw_tb que irá como endereço do registrador no momento do load, e também fornecer o ra_tb que será o endereço
        //onde a informação será lida no registrador. Por fim, é necessário fornecer o we do registrador(weReg_tb) e o we da memória(weReg_tb).
        //*******************************Abaixo é a simulação de um load no registrador: ********************************************************************
    
        wePC_tb = 1;
        weIR_tb =1;
        #10
        clock_tb = 0;
        sinal_tb=0;
        Rw_tb = 1;
        Ra_tb= 0;
        C_tb = 1; // Operação a ser feita (1) -> LOAD (Quero guardar o que está no x0 #0 da memória no endereço 1 do banco de registradores)
        sinalMux1_tb = 0;
        sinalMux2_tb = 0;
        #10
        #10   
        #10

        weReg_tb=1;
        #10
        
      
        // Add -- adicionando o que estava no reg[1] e reg[2] do banco e guardando no reg[3]
        
        Ra_tb = 2;
        Rb_tb = 1;
        Rw_tb = 3;
        C_tb = 3; // Operação a ser feita (3) -> ADD (Quero guardar a soma do x1 e x2 no x3)
        sinalMux1_tb = 1;
        sinalMux2_tb = 1;

        
        #10
        #10
        weReg_tb = 1;
        #10
        weReg_tb = 0;
        //Sub
        C_tb =4;
        Ra_tb = 1;
        Rb_tb = 3;
        Rw_tb = 4;
        sinal_tb = 1;

        #10
        weReg_tb = 1;


      

//*******************************Abaixo é a simulação do store na memória: ********************************************************************
        #10
        Ra_tb = 5;
        Rb_tb = 6;
        weReg_tb = 0;
        sinal_tb = 0;
        sinalMux1_tb = 0;
        sinalMux2_tb = 0;
        C_tb = 2; // Operação a ser feita -> STORE (Quero armazenar no endereço x5 #1 o que está no registrador x6)
        
        #10
        #10
        #10
        weMem_tb=1;

        #10
        
        #10
        weMem_tb=0;
        #10

//*******************************Abaixo é a simulação do addi e subi na memória: ********************************************************************

        #10
        clock_tb = 0;
        sinal_tb=0;
        Rw_tb = 2;
        Ra_tb= 0;
        C_tb = 5; 
        sinalMux1_tb = 0;
        sinalMux2_tb = 1;
        #10
        #10   
        #10

        weReg_tb=1;
        #10

        #10
        clock_tb = 0;
        sinal_tb=0;
        Rw_tb = 7;
        Ra_tb= 0;
        C_tb = 6;
        sinalMux1_tb = 0;
        sinalMux2_tb = 1;
        sinal_tb = 1;
        #10
        #10   
        #10

        weReg_tb=1;
        #10
        




       
$finish;

     
    end

        always #1 clock_tb = ~clock_tb;
    
    



endmodule

aula8demaio/testbench.vcd
$date
	Mon May  8 08:56:53 2023
$end
$version
	Icarus Verilog
$end
$timescale
	1ns
$end
$scope module testbench $end
$var wire 64 ! res_tb [63:0] $end
$var wire 64 " doutMem_tb [63:0] $end
$var wire 32 # doutIR_tb [31:0] $end
$var wire 64 $ doutB_tb [63:0] $end
$var wire 64 % doutA_tb [63:0] $end
$var wire 64 & S2_tb [63:0] $end
$var wire 64 ' S1_tb [63:0] $end
$var wire 64 ( PC_tb [63:0] $end
$var wire 64 ) IR_tb [63:0] $end
$var reg 64 * C_tb [63:0] $end
$var reg 64 + Ra_tb [63:0] $end
$var reg 64 , Rb_tb [63:0] $end
$var reg 64 - Rw_tb [63:0] $end
$var reg 1 . clock_tb $end
$var reg 64 / dinMemIns_tb [63:0] $end
$var reg 1 0 sinalMux1_tb $end
$var reg 1 1 sinalMux2_tb $end
$var reg 1 2 sinal_tb $end
$var reg 1 3 weIR_tb $end
$var reg 1 4 weMemIns_tb $end
$var reg 1 5 weMem_tb $end
$var reg 1 6 wePC_tb $end
$var reg 1 7 weReg_tb $end
$scope module huu $end
$var wire 1 . clock $end
$var wire 1 3 r_enable $end
$var wire 64 8 data_in [63:0] $end
$var reg 32 9 data_out [31:0] $end
$upscope $end
$scope module uhh $end
$var wire 1 . clock $end
$var wire 64 : data_in [63:0] $end
$var wire 1 6 r_enable $end
$var reg 64 ; data_out [63:0] $end
$upscope $end
$scope module utH $end
$var wire 64 < ads [63:0] $end
$var wire 1 . clk $end
$var wire 64 = din [63:0] $end
$var wire 1 4 we $end
$var reg 64 > dout [63:0] $end
$upscope $end
$scope module utt $end
$var wire 64 ? Ra [63:0] $end
$var wire 64 @ Rb [63:0] $end
$var wire 64 A Rw [63:0] $end
$var wire 1 . clk $end
$var wire 1 7 we $end
$var wire 64 B din [63:0] $end
$var reg 64 C doutA [63:0] $end
$var reg 64 D doutB [63:0] $end
$upscope $end
$scope module utu $end
$var wire 1 . clk $end
$var wire 64 E din [63:0] $end
$var wire 1 5 we $end
$var wire 64 F ads [63:0] $end
$var reg 64 G dout [63:0] $end
$upscope $end
$scope module utv $end
$var wire 32 H C [31:0] $end
$var wire 64 I Rb [63:0] $end
$var wire 1 0 sinalMux $end
$var wire 64 J S1 [63:0] $end
$upscope $end
$scope module uut $end
$var wire 64 K a [63:0] $end
$var wire 64 L b [63:0] $end
$var wire 1 2 sinal $end
$var wire 64 M soma [63:0] $end
$upscope $end
$scope module uvv $end
$var wire 64 N dout [63:0] $end
$var wire 1 1 sinalMux $end
$var wire 64 O soma [63:0] $end
$var wire 64 P S2 [63:0] $end
$upscope $end
$upscope $end
$enddefinitions $end
#0
$dumpvars
bx P
bx O
bx N
bx M
bx L
bx K
bx J
bx I
bx H
bx G
bx F
bx E
bx D
bx C
bx B
bx A
bx @
bx ?
bx >
bx =
bx <
bx ;
bx :
bx 9
bx 8
x7
16
x5
x4
13
x2
x1
x0
bx /
x.
bx -
bx ,
bx +
bx *
bx )
bx (
bx '
bx &
bx %
bx $
bx #
bx "
bx !
$end
#10
b1 %
b1 C
b1 K
b1 (
b1 ;
b1 <
b0xxxxxxxxxxxx '
b0xxxxxxxxxxxx J
b0xxxxxxxxxxxx L
01
00
b1 *
b1 :
b0 +
b0 ?
b1 -
b1 A
02
1.
#11
0.
#12
b0 )
b0 8
b0 >
1.
#13
0.
#14
b1 !
b1 F
b1 M
b1 O
b0 '
b0 J
b0 L
b0 #
b0 9
b0 H
1.
#15
0.
#16
b1011 &
b1011 B
b1011 P
b1011 "
b1011 G
b1011 N
1.
#17
0.
#18
1.
#19
0.
#20
1.
#21
0.
#22
1.
#23
0.
#24
1.
#25
0.
#26
1.
#27
0.
#28
1.
#29
0.
#30
1.
#31
0.
#32
1.
#33
0.
#34
1.
#35
0.
#36
1.
#37
0.
#38
1.
#39
0.
#40
1.
17
#41
0.
#42
1.
#43
0.
#44
1.
#45
0.
#46
1.
#47
0.
#48
1.
#49
0.
#50
b1011 $
b1011 D
b1011 E
b1011 I
b11 %
b11 C
b11 K
b11 (
b11 ;
b11 <
b1110 !
b1110 F
b1110 M
b1110 O
b1110 &
b1110 B
b1110 P
b1011 '
b1011 J
b1011 L
1.
11
10
b11 *
b11 :
b11 -
b11 A
b1 ,
b1 @
b10 +
b10 ?
#51
0.
#52
b100001 )
b100001 8
b100001 >
bx "
bx G
bx N
1.
#53
0.
#54
b100001 #
b100001 9
b100001 H
1.
#55
0.
#56
1.
#57
0.
#58
1.
#59
0.
#60
1.
#61
0.
#62
1.
#63
0.
#64
1.
#65
0.
#66
1.
#67
0.
#68
1.
#69
0.
#70
1.
#71
0.
#72
1.
#73
0.
#74
1.
#75
0.
#76
1.
#77
0.
#78
1.
#79
0.
#80
b1110 '
b1110 J
b1110 L
b100 (
b100 ;
b100 <
b1110 $
b1110 D
b1110 E
b1110 I
b1011 %
b1011 C
b1011 K
b1111111111111111111111111111111111111111111111111111111111111101 &
b1111111111111111111111111111111111111111111111111111111111111101 B
b1111111111111111111111111111111111111111111111111111111111111101 P
b1111111111111111111111111111111111111111111111111111111111111101 !
b1111111111111111111111111111111111111111111111111111111111111101 F
b1111111111111111111111111111111111111111111111111111111111111101 M
b1111111111111111111111111111111111111111111111111111111111111101 O
1.
12
b100 -
b100 A
b11 ,
b11 @
b1 +
b1 ?
b100 *
b100 :
07
#81
0.
#82
1.
#83
0.
#84
1.
#85
0.
#86
1.
#87
0.
#88
1.
#89
0.
#90
1.
17
#91
0.
#92
1.
#93
0.
#94
1.
#95
0.
#96
1.
#97
0.
#98
1.
#99
0.
#100
b10 (
b10 ;
b10 <
b100100 $
b100100 D
b100100 E
b100100 I
b10 %
b10 C
b10 K
bx &
bx B
bx P
b0 '
b0 J
b0 L
b10 !
b10 F
b10 M
b10 O
1.
b10 *
b10 :
01
00
02
07
b110 ,
b110 @
b101 +
b101 ?
#101
0.
#102
b100000000000000100001 )
b100000000000000100001 8
b100000000000000100001 >
1.
#103
0.
#104
b11 !
b11 F
b11 M
b11 O
b1 '
b1 J
b1 L
b100000000000000100001 #
b100000000000000100001 9
b100000000000000100001 H
1.
#105
0.
#106
1.
#107
0.
#108
1.
#109
0.
#110
1.
#111
0.
#112
1.
#113
0.
#114
1.
#115
0.
#116
1.
#117
0.
#118
1.
#119
0.
#120
1.
#121
0.
#122
1.
#123
0.
#124
1.
#125
0.
#126
1.
#127
0.
#128
1.
#129
0.
#130
1.
15
#131
0.
#132
1.
#133
0.
#134
1.
#135
0.
#136
1.
#137
0.
#138
1.
#139
0.
#140
1.
#141
0.
#142
1.
#143
0.
#144
1.
#145
0.
#146
1.
#147
0.
#148
1.
#149
0.
#150
b100100 &
b100100 B
b100100 P
b100100 "
b100100 G
b100100 N
1.
05
#151
0.
#152
1.
#153
0.
#154
1.
#155
0.
#156
1.
#157
0.
#158
1.
#159
0.
#160
1.
#161
0.
#162
1.
#163
0.
#164
1.
#165
0.
#166
1.
#167
0.
#168
1.
#169
0.
#170
b10 !
b10 F
b10 M
b10 O
b1 %
b1 C
b1 K
b101 (
b101 ;
b101 <
b10 &
b10 B
b10 P
1.
11
b101 *
b101 :
b0 +
b0 ?
b10 -
b10 A
#171
0.
#172
bx "
bx G
bx N
1.
#173
0.
#174
1.
#175
0.
#176
1.
#177
0.
#178
1.
#179
0.
#180
1.
#181
0.
#182
1.
#183
0.
#184
1.
#185
0.
#186
1.
#187
0.
#188
1.
#189
0.
#190
1.
#191
0.
#192
1.
#193
0.
#194
1.
#195
0.
#196
1.
#197
0.
#198
1.
#199
0.
#200
1.
17
#201
0.
#202
1.
#203
0.
#204
1.
#205
0.
#206
1.
#207
0.
#208
1.
#209
0.
#210
1.
#211
0.
#212
1.
#213
0.
#214
1.
#215
0.
#216
1.
#217
0.
#218
1.
#219
0.
#220
b110 (
b110 ;
b110 <
b0 &
b0 B
b0 P
b0 !
b0 F
b0 M
b0 O
1.
12
b110 *
b110 :
b111 -
b111 A
#221
0.
#222
b101101 "
b101101 G
b101101 N
b1000000000000000100001 )
b1000000000000000100001 8
b1000000000000000100001 >
1.
#223
0.
#224
b1111111111111111111111111111111111111111111111111111111111111111 &
b1111111111111111111111111111111111111111111111111111111111111111 B
b1111111111111111111111111111111111111111111111111111111111111111 P
b1111111111111111111111111111111111111111111111111111111111111111 !
b1111111111111111111111111111111111111111111111111111111111111111 F
b1111111111111111111111111111111111111111111111111111111111111111 M
b1111111111111111111111111111111111111111111111111111111111111111 O
b10 '
b10 J
b10 L
b1000000000000000100001 #
b1000000000000000100001 9
b1000000000000000100001 H
1.
#225
0.
#226
bx "
bx G
bx N
1.
