floatingpoint_multiplica/fd.v
module fd(multiplicador, multiplicando, produto, clock, sinalMuxFP1, sinalMuxFP2, sinalRound, sinalShiftRes, sinalIncOrDec, round_fract, ula, reset);

input [31:0] multiplicador;
input [31:0] multiplicando;
input sinalMuxFP1, sinalMuxFP2, sinalRound;
input [8:0] sinalIncOrDec;
input [8:0] sinalShiftRes;
input clock, reset;
output [31:0] produto;
output [53:0] ula;
output [25:0] round_fract;

wire [7:0] soma_exp;
wire sinal;
wire [7:0] mux1_out;
wire [27:0] mux2_out;
wire [7:0] round_exp_out;
wire [7:0] round_exp_in;
wire [25:0] round_fract_out;

wire [27:0] shift_res_out;
wire [53:0] ula_out;

assign sinal = multiplicador[31]^multiplicando[31]; //  0 1 -> 1, 1 0 -> 1, 0 0 -> 0, 1 1 -> 0
assign ula = ula_out; // Saida da ula
assign round_fract = round_fract_out;
assign produto = {shift_res_out[27], round_exp_out, round_fract_out[25:3]};


ULA_exp ULA_exp(
    .exp1(multiplicador[30:23]),
    .exp2(multiplicando[30:23]),
    .soma_exp(soma_exp)
);

MuxFP1 mux_fp1 (
    .exp1(soma_exp),
    .exp2(round_exp_out),
    .sinalMuxFP1(sinalMuxFP1),
    .exp(mux1_out)

);

shift_res shift_res (
    .b(mux2_out),
    .sinal(sinalShiftRes),
    .res(shift_res_out)
);

MuxFP2 mux_fp2 (
    .fraction1({sinal,ula_out[53:27]}),
    .fraction2({sinal, 1'b1, round_fract}),
    .sinalMuxFP2(sinalMuxFP2),
    .fraction(mux2_out)
);

ULA_Float ula_f(
    .multiplicador({1'b1, multiplicador[22:0], 3'b000}),
    .multiplicando({1'b1, multiplicando[22:0], 3'b000}),
    .produto(ula_out),
    .reset(reset),
    .clock(clock)
);

ULA_exp_one ula_exp_one(
    .b(mux1_out),
    .sinal(sinalIncOrDec),
    .res(round_exp_in)
);

round round(
    .exp_inicial(round_exp_in),
    .exp_final(round_exp_out),
    .fract_inicial(shift_res_out[26:1]),
    .fract_final(round_fract_out),
    .clock(clock),
    .sinal(sinalRound)
);

endmodule

module ULA_exp(exp1, exp2, soma_exp);

input [7:0] exp1;
input [7:0] exp2;
output [7:0] soma_exp;

assign soma_exp = (exp1-127) + (exp2-127) + 2'b10; 

endmodule

module round(exp_inicial, fract_inicial, exp_final, fract_final, sinal, clock);

input clock;
input [7:0] exp_inicial;
output reg [7:0] exp_final;
input [25:0] fract_inicial;
output reg [25:0] fract_final;
wire [25:0] arredondado;
input sinal;

assign arredondado = (fract_inicial[2:0] == 3'b111) ? ({fract_inicial[25:3]+1'b1, 3'b000}):
                           (fract_inicial[2:0] == 3'b101) ? ({fract_inicial[25:3]+1'b1, 3'b000}):
                           (fract_inicial[2:0] == 3'b110) ? ({fract_inicial[25:3]+1'b1, 3'b000}):
                           (fract_inicial[2:0] == 3'b100 && fract_inicial[3]==1'b1) ? ({fract_inicial[25:3]+1'b1, 3'b000}):
                            {fract_inicial[25:3], 3'b000};

always @(posedge clock)
begin   
    if(sinal) begin
        fract_final <= arredondado; 
    end
    else begin
        fract_final <= fract_inicial;
    end
    exp_final <= exp_inicial;

end
                           
endmodule

module ULA_exp_one (b, sinal, res);

input [7:0] b; 
input [8:0] sinal;
output [7:0] res;

assign res = (sinal[8] == 1'b0) ? (b+sinal[7:0]+127):
                                  (b-sinal[7:0]+127); 
     
endmodule

module shift_res(b, sinal, res);

input [27:0] b;
input [8:0] sinal; //o bit mais significativo pra indicar se é direita ou esquerda e 8 bits do expoente. Ainda nao sei exatamente qual será esse sinal 
output [27:0] res;

assign res = (sinal[8] == 1)? {b[27], b[26:0] << sinal[7:0]}:
                            {b[27], b[26:0] >> sinal[7:0]};

endmodule

module MuxFP1 (exp1, exp2, sinalMuxFP1, exp);

input [7:0] exp1;
input [7:0] exp2;
output [7:0] exp; // Será incrementado ou decrementado
input sinalMuxFP1;

assign exp = (sinalMuxFP1 == 1'b0) ? (exp1) : (exp2);

endmodule

module MuxFP2 (fraction1, fraction2, sinalMuxFP2, fraction);

input [27:0] fraction1;
input [27:0] fraction2;
output [27:0] fraction; // receberá shift para a direita ou esquerda
input sinalMuxFP2;

assign fraction = (sinalMuxFP2 == 1'b0) ? (fraction1) : (fraction2);

endmodule

floatingpoint_multiplica/ULA_Float.v
module ULA_Float(multiplicador, multiplicando, produto, reset, clock);

input [26:0] multiplicador;
input [26:0] multiplicando;
input reset;
input clock;
output [53:0] produto;

wire [54:0] produto_in;
wire [54:0] produto_out;
wire [54:0] produto_soma;
wire [26:0] multiplicador_shift_in;
wire [26:0] multiplicador_shift_out;
wire [53:0] multiplicando_shift_in;
wire [53:0] multiplicando_shift_out;
wire [54:0] produto_shift;
wire [4:0] N_out;
wire [4:0] N_in;
wire done;

registrador_soma regA (
    .reset(reset),
    .clock(clock),
    .data_in(produto_soma),
    .data_out(produto_out)
);

registrador_N reg_N (
    .reset(reset),
    .clock(clock),
    .data_out(N_out),
    .data_in(N_in),
    .done(done)
);

subtracao sub(
    .N(N_out),
    .reset(reset),
    .sub(N_in)
);

registrador_multiplicador multR(
    .data_in(multiplicador_shift_in),
    .data_out(multiplicador_shift_out),
    .clock(clock),
    .reset(reset)
);

registrador_multiplicando multD(
    .data_in(multiplicando_shift_in),
    .data_out(multiplicando_shift_out),
    .clock(clock),
    .reset(reset)
);


assign multiplicador_shift_in = (reset) ? multiplicador: multiplicador_shift_out >> 1; //Shift do multiplicador
assign multiplicando_shift_in = (reset) ? {27'b0, multiplicando}: multiplicando_shift_out << 1; // Shift do multiplicando
assign produto_soma = (multiplicador_shift_out[0] == 1) ? (produto_out + multiplicando_shift_out): produto_out; // Soma
assign produto = (done) ? produto_soma: 9'bz; // Produto final

endmodule

module registrador_multiplicador(data_in, data_out, clock, reset);

input             clock;
input      [26:0] data_in;
input               reset;
output  reg   [26:0] data_out;

always @(posedge clock or posedge reset)
begin   
            data_out <= data_in; 

end
endmodule

module registrador_multiplicando(data_in, data_out, clock, reset);

input             clock;
input      [53:0] data_in;
input               reset;
output  reg   [53:0] data_out;

always @(posedge clock or posedge reset)
begin   
            data_out <= data_in; 

end
endmodule

module registrador_soma(clock, data_in, data_out, reset);

input             clock;
input      [54:0] data_in;
input               reset;
output  reg   [54:0] data_out;

always @(posedge clock or posedge reset)
begin   
        if(reset) 
            data_out <=0;
        else 
            data_out <= data_in[54:0]; 

end
endmodule

module subtracao(N, sub, reset);

input [4:0]  N;
input reset;
output [4:0] sub;

assign sub = (~reset) ? N - 1 : N;

endmodule

module registrador_N(clock, data_out, data_in, reset, done);

input             clock;
input               reset;
output  reg   [4:0] data_out;
input           [4:0] data_in;
output   reg          done;

always @(posedge clock or posedge reset)
begin   
        if(reset) begin
            done <=0;
            data_out <= 5'b11011;
        end
        else 
            data_out <= data_in[4:0]; 
            if(data_in == 0)
                done <= 1;

end
endmodule

floatingpoint_multiplica/tb_mult.v
// **********GRUPO ************
// Helena Bianchi Moyen
// Luiz Mariano
// Mariana Watanabe


`timescale 1ns/1ns

module testbench;

    wire [31:0] produto_tb;
    reg clock_tb;
    reg reset_tb;
    reg sinalMuxFP1_tb, sinalRound_tb, sinalMuxFP2_tb;
    reg [31:0] multiplicando_tb;
    reg [31:0] multiplicador_tb;
    reg [8:0] sinalShiftRes_tb;
    reg [8:0] sinalIncOrDec_tb;
    wire [25:0] round_fract_tb;
    wire [53:0] ula_tb;

    fd fd(
        .multiplicador(multiplicador_tb), 
        .multiplicando(multiplicando_tb),
        .produto(produto_tb),
        .clock(clock_tb),
        .sinalMuxFP1(sinalMuxFP1_tb), 
        .sinalShiftRes(sinalShiftRes_tb), 
        .sinalIncOrDec(sinalIncOrDec_tb), 
        .round_fract(round_fract_tb),
        .ula(ula_tb), 
        .reset(reset_tb),
        .sinalRound(sinalRound_tb),
        .sinalMuxFP2(sinalMuxFP2_tb)

        );

    initial $dumpfile("testbench.vcd");
    initial $dumpvars(0, testbench);

    initial 
    begin
        
        //*******************************Abaixo é a simulação: ********************************************************************

        clock_tb  = 0;
        #1
        reset_tb = 1;
        multiplicador_tb = 32'b00111111101001010110000001000010; //1.292
        multiplicando_tb = 32'b00111111110000000000000000000000;//1.5
        sinalMuxFP2_tb = 0; 
        sinalMuxFP1_tb = 0;
        sinalShiftRes_tb  = 9'b100000010; // shift de dois para esquerda 
        sinalIncOrDec_tb  = 9'b100000010;
        #10
        reset_tb = 0;
        #1000
        $display("Fim da simulação: %b", produto_tb);
        $finish;

     
    end

        always #10 clock_tb = ~clock_tb;
    
    

endmodule

floatingpoint_multiplica/testbench.vcd
$date
	Fri Jun 23 13:12:26 2023
$end
$version
	Icarus Verilog
$end
$timescale
	1ns
$end
$scope module testbench $end
$var wire 54 ! ula_tb [53:0] $end
$var wire 26 " round_fract_tb [25:0] $end
$var wire 32 # produto_tb [31:0] $end
$var reg 1 $ clock_tb $end
$var reg 32 % multiplicador_tb [31:0] $end
$var reg 32 & multiplicando_tb [31:0] $end
$var reg 1 ' reset_tb $end
$var reg 9 ( sinalIncOrDec_tb [8:0] $end
$var reg 1 ) sinalMuxFP1_tb $end
$var reg 1 * sinalMuxFP2_tb $end
$var reg 1 + sinalRound_tb $end
$var reg 9 , sinalShiftRes_tb [8:0] $end
$scope module fd $end
$var wire 1 $ clock $end
$var wire 32 - multiplicador [31:0] $end
$var wire 32 . multiplicando [31:0] $end
$var wire 1 ' reset $end
$var wire 26 / round_fract [25:0] $end
$var wire 1 0 sinal $end
$var wire 9 1 sinalIncOrDec [8:0] $end
$var wire 1 ) sinalMuxFP1 $end
$var wire 1 * sinalMuxFP2 $end
$var wire 1 + sinalRound $end
$var wire 9 2 sinalShiftRes [8:0] $end
$var wire 54 3 ula [53:0] $end
$var wire 54 4 ula_out [53:0] $end
$var wire 8 5 soma_exp [7:0] $end
$var wire 28 6 shift_res_out [27:0] $end
$var wire 26 7 round_fract_out [25:0] $end
$var wire 8 8 round_exp_out [7:0] $end
$var wire 8 9 round_exp_in [7:0] $end
$var wire 32 : produto [31:0] $end
$var wire 28 ; mux2_out [27:0] $end
$var wire 8 < mux1_out [7:0] $end
$scope module ULA_exp $end
$var wire 8 = exp1 [7:0] $end
$var wire 8 > exp2 [7:0] $end
$var wire 8 ? soma_exp [7:0] $end
$upscope $end
$scope module mux_fp1 $end
$var wire 8 @ exp1 [7:0] $end
$var wire 1 ) sinalMuxFP1 $end
$var wire 8 A exp2 [7:0] $end
$var wire 8 B exp [7:0] $end
$upscope $end
$scope module mux_fp2 $end
$var wire 28 C fraction1 [27:0] $end
$var wire 28 D fraction2 [27:0] $end
$var wire 1 * sinalMuxFP2 $end
$var wire 28 E fraction [27:0] $end
$upscope $end
$scope module round $end
$var wire 1 $ clock $end
$var wire 26 F fract_inicial [25:0] $end
$var wire 1 + sinal $end
$var wire 8 G exp_inicial [7:0] $end
$var wire 26 H arredondado [25:0] $end
$var reg 8 I exp_final [7:0] $end
$var reg 26 J fract_final [25:0] $end
$upscope $end
$scope module shift_res $end
$var wire 28 K b [27:0] $end
$var wire 9 L sinal [8:0] $end
$var wire 28 M res [27:0] $end
$upscope $end
$scope module ula_exp_one $end
$var wire 8 N b [7:0] $end
$var wire 9 O sinal [8:0] $end
$var wire 8 P res [7:0] $end
$upscope $end
$scope module ula_f $end
$var wire 1 $ clock $end
$var wire 27 Q multiplicador [26:0] $end
$var wire 27 R multiplicando [26:0] $end
$var wire 1 ' reset $end
$var wire 55 S produto_soma [54:0] $end
$var wire 55 T produto_out [54:0] $end
$var wire 54 U produto [53:0] $end
$var wire 54 V multiplicando_shift_out [53:0] $end
$var wire 54 W multiplicando_shift_in [53:0] $end
$var wire 27 X multiplicador_shift_out [26:0] $end
$var wire 27 Y multiplicador_shift_in [26:0] $end
$var wire 1 Z done $end
$var wire 5 [ N_out [4:0] $end
$var wire 5 \ N_in [4:0] $end
$scope module multD $end
$var wire 1 $ clock $end
$var wire 54 ] data_in [53:0] $end
$var wire 1 ' reset $end
$var reg 54 ^ data_out [53:0] $end
$upscope $end
$scope module multR $end
$var wire 1 $ clock $end
$var wire 27 _ data_in [26:0] $end
$var wire 1 ' reset $end
$var reg 27 ` data_out [26:0] $end
$upscope $end
$scope module regA $end
$var wire 1 $ clock $end
$var wire 55 a data_in [54:0] $end
$var wire 1 ' reset $end
$var reg 55 b data_out [54:0] $end
$upscope $end
$scope module reg_N $end
$var wire 1 $ clock $end
$var wire 1 ' reset $end
$var wire 5 c data_in [4:0] $end
$var reg 5 d data_out [4:0] $end
$var reg 1 Z done $end
$upscope $end
$scope module sub $end
$var wire 5 e N [4:0] $end
$var wire 1 ' reset $end
$var wire 5 f sub [4:0] $end
$upscope $end
$upscope $end
$upscope $end
$upscope $end
$enddefinitions $end
#0
$dumpvars
bx f
bx e
bx d
bx c
bx b
bx a
bx `
bx _
bx ^
bx0 ]
bx \
bx [
xZ
bx Y
bx X
bx0 W
bx V
bx U
bx T
bx S
b1xxxxxxxxxxxxxxxxxxxxxxx000 R
b1xxxxxxxxxxxxxxxxxxxxxxx000 Q
bx P
bx O
bx N
bx M
bx L
bx K
bx J
bx I
bx000 H
bx G
bx F
bx E
bx1xxxxxxxxxxxxxxxxxxxxxxxxxx D
bx C
bx B
bx A
bx @
bx ?
bx >
bx =
bx <
bx ;
bx :
bx 9
bx 8
bx 7
bx 6
bx 5
bx 4
bx 3
bx 2
bx 1
x0
bx /
bx .
bx -
bx ,
x+
x*
x)
bx (
x'
bx &
bx %
0$
bx #
bx "
bx !
$end
#1
b0 H
b0zzzzzzzzz !
b0zzzzzzzzz 3
b0zzzzzzzzz 4
b0zzzzzzzzz U
b11011 \
b11011 c
b11011 f
b0 T
b0 b
b11011 [
b11011 d
b11011 e
0Z
bx0 V
bx0 ^
b0xxxxxxxxxxxxxxxxxxxxxxxxxxxxxxx #
b0xxxxxxxxxxxxxxxxxxxxxxxxxxxxxxx :
b0 F
b1111111 9
b1111111 G
b1111111 P
b0 6
b0 M
b0 ;
b0 E
b0 K
b10 <
b10 B
b10 N
b0 C
b1xxxxxxxxxxxxxxxxxxxxxxxxxx D
00
b10 5
b10 ?
b10 @
b1111111 >
b110000000000000000000000000 R
b1111111 =
b101001010110000001000010000 Q
b101001010110000001000010000 Y
b101001010110000001000010000 _
b110000000000000000000000000 W
b110000000000000000000000000 ]
b100000010 (
b100000010 1
b100000010 O
b100000010 ,
b100000010 2
b100000010 L
0)
0*
b111111110000000000000000000000 &
b111111110000000000000000000000 .
b111111101001010110000001000010 %
b111111101001010110000001000010 -
1'
#10
b0 S
b0 a
b111111100000000000000000000000 #
b111111100000000000000000000000 :
b1111111 8
b1111111 A
b1111111 I
b100000000000000000000000000 D
b0 "
b0 /
b0 7
b0 J
b110000000000000000000000000 V
b110000000000000000000000000 ^
b101001010110000001000010000 X
b101001010110000001000010000 `
1$
#11
b11010 \
b11010 c
b11010 f
b10100101011000000100001000 Y
b10100101011000000100001000 _
b1100000000000000000000000000 W
b1100000000000000000000000000 ]
0'
#20
0$
#30
b1010010101100000010000100 Y
b1010010101100000010000100 _
b11000000000000000000000000000 W
b11000000000000000000000000000 ]
b11001 \
b11001 c
b11001 f
b11010 [
b11010 d
b11010 e
b10100101011000000100001000 X
b10100101011000000100001000 `
b1100000000000000000000000000 V
b1100000000000000000000000000 ^
1$
#40
0$
#50
b110000000000000000000000000000 W
b110000000000000000000000000000 ]
b101001010110000001000010 Y
b101001010110000001000010 _
b11000 \
b11000 c
b11000 f
b11000000000000000000000000000 V
b11000000000000000000000000000 ^
b1010010101100000010000100 X
b1010010101100000010000100 `
b11001 [
b11001 d
b11001 e
1$
#60
0$
#70
b10100101011000000100001 Y
b10100101011000000100001 _
b1100000000000000000000000000000 W
b1100000000000000000000000000000 ]
b10111 \
b10111 c
b10111 f
b11000 [
b11000 d
b11000 e
b101001010110000001000010 X
b101001010110000001000010 `
b110000000000000000000000000000 V
b110000000000000000000000000000 ^
1$
#80
0$
#90
b11000000000000000000000000000000 W
b11000000000000000000000000000000 ]
b1100000000000000000000000000000 S
b1100000000000000000000000000000 a
b1010010101100000010000 Y
b1010010101100000010000 _
b10110 \
b10110 c
b10110 f
b1100000000000000000000000000000 V
b1100000000000000000000000000000 ^
b10100101011000000100001 X
b10100101011000000100001 `
b10111 [
b10111 d
b10111 e
1$
#100
0$
#110
b101001010110000001000 Y
b101001010110000001000 _
b110000000000000000000000000000000 W
b110000000000000000000000000000000 ]
b10101 \
b10101 c
b10101 f
b1100000000000000000000000000000 S
b1100000000000000000000000000000 a
b1100000000000000000000000000000 T
b1100000000000000000000000000000 b
b10110 [
b10110 d
b10110 e
b1010010101100000010000 X
b1010010101100000010000 `
b11000000000000000000000000000000 V
b11000000000000000000000000000000 ^
1$
#120
0$
#130
b1100000000000000000000000000000000 W
b1100000000000000000000000000000000 ]
b10100101011000000100 Y
b10100101011000000100 _
b10100 \
b10100 c
b10100 f
b110000000000000000000000000000000 V
b110000000000000000000000000000000 ^
b101001010110000001000 X
b101001010110000001000 `
b10101 [
b10101 d
b10101 e
1$
#140
0$
#150
b1010010101100000010 Y
b1010010101100000010 _
b11000000000000000000000000000000000 W
b11000000000000000000000000000000000 ]
b10011 \
b10011 c
b10011 f
b10100 [
b10100 d
b10100 e
b10100101011000000100 X
b10100101011000000100 `
b1100000000000000000000000000000000 V
b1100000000000000000000000000000000 ^
1$
#160
0$
#170
b110000000000000000000000000000000000 W
b110000000000000000000000000000000000 ]
b101001010110000001 Y
b101001010110000001 _
b10010 \
b10010 c
b10010 f
b11000000000000000000000000000000000 V
b11000000000000000000000000000000000 ^
b1010010101100000010 X
b1010010101100000010 `
b10011 [
b10011 d
b10011 e
1$
#180
0$
#190
b110001100000000000000000000000000000 S
b110001100000000000000000000000000000 a
b10100101011000000 Y
b10100101011000000 _
b1100000000000000000000000000000000000 W
b1100000000000000000000000000000000000 ]
b10001 \
b10001 c
b10001 f
b10010 [
b10010 d
b10010 e
b101001010110000001 X
b101001010110000001 `
b110000000000000000000000000000000000 V
b110000000000000000000000000000000000 ^
1$
#200
0$
#210
b11000000000000000000000000000000000000 W
b11000000000000000000000000000000000000 ]
b1010010101100000 Y
b1010010101100000 _
b10000 \
b10000 c
b10000 f
b110001100000000000000000000000000000 S
b110001100000000000000000000000000000 a
b1100000000000000000000000000000000000 V
b1100000000000000000000000000000000000 ^
b10100101011000000 X
b10100101011000000 `
b10001 [
b10001 d
b10001 e
b110001100000000000000000000000000000 T
b110001100000000000000000000000000000 b
1$
#220
0$
#230
b101001010110000 Y
b101001010110000 _
b110000000000000000000000000000000000000 W
b110000000000000000000000000000000000000 ]
b1111 \
b1111 c
b1111 f
b10000 [
b10000 d
b10000 e
b1010010101100000 X
b1010010101100000 `
b11000000000000000000000000000000000000 V
b11000000000000000000000000000000000000 ^
1$
#240
0$
#250
b1100000000000000000000000000000000000000 W
b1100000000000000000000000000000000000000 ]
b10100101011000 Y
b10100101011000 _
b1110 \
b1110 c
b1110 f
b110000000000000000000000000000000000000 V
b110000000000000000000000000000000000000 ^
b101001010110000 X
b101001010110000 `
b1111 [
b1111 d
b1111 e
1$
#260
0$
#270
b1010010101100 Y
b1010010101100 _
b11000000000000000000000000000000000000000 W
b11000000000000000000000000000000000000000 ]
b1101 \
b1101 c
b1101 f
b1110 [
b1110 d
b1110 e
b10100101011000 X
b10100101011000 `
b1100000000000000000000000000000000000000 V
b1100000000000000000000000000000000000000 ^
1$
#280
0$
#290
b110000000000000000000000000000000000000000 W
b110000000000000000000000000000000000000000 ]
b101001010110 Y
b101001010110 _
b1100 \
b1100 c
b1100 f
b11000000000000000000000000000000000000000 V
b11000000000000000000000000000000000000000 ^
b1010010101100 X
b1010010101100 `
b1101 [
b1101 d
b1101 e
1$
#300
0$
#310
b10100101011 Y
b10100101011 _
b1100000000000000000000000000000000000000000 W
b1100000000000000000000000000000000000000000 ]
b1011 \
b1011 c
b1011 f
b1100 [
b1100 d
b1100 e
b101001010110 X
b101001010110 `
b110000000000000000000000000000000000000000 V
b110000000000000000000000000000000000000000 ^
1$
#320
0$
#330
b11000000000000000000000000000000000000000000 W
b11000000000000000000000000000000000000000000 ]
b1100000110001100000000000000000000000000000 S
b1100000110001100000000000000000000000000000 a
b1010010101 Y
b1010010101 _
b1010 \
b1010 c
b1010 f
b1100000000000000000000000000000000000000000 V
b1100000000000000000000000000000000000000000 ^
b10100101011 X
b10100101011 `
b1011 [
b1011 d
b1011 e
1$
#340
0$
#350
b101001010 Y
b101001010 _
b110000000000000000000000000000000000000000000 W
b110000000000000000000000000000000000000000000 ]
b1001 \
b1001 c
b1001 f
b100100000110001100000000000000000000000000000 S
b100100000110001100000000000000000000000000000 a
b1100000110001100000000000000000000000000000 T
b1100000110001100000000000000000000000000000 b
b1010 [
b1010 d
b1010 e
b1010010101 X
b1010010101 `
b11000000000000000000000000000000000000000000 V
b11000000000000000000000000000000000000000000 ^
1$
#360
0$
#370
b1100000000000000000000000000000000000000000000 W
b1100000000000000000000000000000000000000000000 ]
b10100101 Y
b10100101 _
b1000 \
b1000 c
b1000 f
b100100000110001100000000000000000000000000000 S
b100100000110001100000000000000000000000000000 a
b110000000000000000000000000000000000000000000 V
b110000000000000000000000000000000000000000000 ^
b101001010 X
b101001010 `
b1001 [
b1001 d
b1001 e
b100100000110001100000000000000000000000000000 T
b100100000110001100000000000000000000000000000 b
1$
#380
0$
#390
b10000100000110001100000000000000000000000000000 S
b10000100000110001100000000000000000000000000000 a
b1010010 Y
b1010010 _
b11000000000000000000000000000000000000000000000 W
b11000000000000000000000000000000000000000000000 ]
b111 \
b111 c
b111 f
b1000 [
b1000 d
b1000 e
b10100101 X
b10100101 `
b1100000000000000000000000000000000000000000000 V
b1100000000000000000000000000000000000000000000 ^
1$
#400
0$
#410
b110000000000000000000000000000000000000000000000 W
b110000000000000000000000000000000000000000000000 ]
b101001 Y
b101001 _
b110 \
b110 c
b110 f
b10000100000110001100000000000000000000000000000 S
b10000100000110001100000000000000000000000000000 a
b11000000000000000000000000000000000000000000000 V
b11000000000000000000000000000000000000000000000 ^
b1010010 X
b1010010 `
b111 [
b111 d
b111 e
b10000100000110001100000000000000000000000000000 T
b10000100000110001100000000000000000000000000000 b
1$
#420
0$
#430
b1000000100000110001100000000000000000000000000000 S
b1000000100000110001100000000000000000000000000000 a
b10100 Y
b10100 _
b1100000000000000000000000000000000000000000000000 W
b1100000000000000000000000000000000000000000000000 ]
b101 \
b101 c
b101 f
b110 [
b110 d
b110 e
b101001 X
b101001 `
b110000000000000000000000000000000000000000000000 V
b110000000000000000000000000000000000000000000000 ^
1$
#440
0$
#450
b11000000000000000000000000000000000000000000000000 W
b11000000000000000000000000000000000000000000000000 ]
b1010 Y
b1010 _
b100 \
b100 c
b100 f
b1000000100000110001100000000000000000000000000000 S
b1000000100000110001100000000000000000000000000000 a
b1100000000000000000000000000000000000000000000000 V
b1100000000000000000000000000000000000000000000000 ^
b10100 X
b10100 `
b101 [
b101 d
b101 e
b1000000100000110001100000000000000000000000000000 T
b1000000100000110001100000000000000000000000000000 b
1$
#460
0$
#470
b101 Y
b101 _
b110000000000000000000000000000000000000000000000000 W
b110000000000000000000000000000000000000000000000000 ]
b11 \
b11 c
b11 f
b100 [
b100 d
b100 e
b1010 X
b1010 `
b11000000000000000000000000000000000000000000000000 V
b11000000000000000000000000000000000000000000000000 ^
1$
#480
0$
#490
b1100000000000000000000000000000000000000000000000000 W
b1100000000000000000000000000000000000000000000000000 ]
b111000000100000110001100000000000000000000000000000 S
b111000000100000110001100000000000000000000000000000 a
b10 Y
b10 _
b10 \
b10 c
b10 f
b110000000000000000000000000000000000000000000000000 V
b110000000000000000000000000000000000000000000000000 ^
b101 X
b101 `
b11 [
b11 d
b11 e
1$
#500
0$
#510
b1 Y
b1 _
b11000000000000000000000000000000000000000000000000000 W
b11000000000000000000000000000000000000000000000000000 ]
b1 \
b1 c
b1 f
b111000000100000110001100000000000000000000000000000 S
b111000000100000110001100000000000000000000000000000 a
b111000000100000110001100000000000000000000000000000 T
b111000000100000110001100000000000000000000000000000 b
b10 [
b10 d
b10 e
b10 X
b10 `
b1100000000000000000000000000000000000000000000000000 V
b1100000000000000000000000000000000000000000000000000 ^
1$
#520
0$
#530
b110000000000000000000000000000000000000000000000000000 W
b110000000000000000000000000000000000000000000000000000 ]
b11111000000100000110001100000000000000000000000000000 S
b11111000000100000110001100000000000000000000000000000 a
b0 Y
b0 _
b0 \
b0 c
b0 f
b11000000000000000000000000000000000000000000000000000 V
b11000000000000000000000000000000000000000000000000000 ^
b1 X
b1 `
b1 [
b1 d
b1 e
1$
#540
0$
#550
b11110000001000001100011000 H
b11110000001000001100011000 F
b111100000010000011000110000 6
b111100000010000011000110000 M
b11111000000100000110001100 ;
b11111000000100000110001100 E
b11111000000100000110001100 K
b11111000000100000110001100 C
b11111000000100000110001100000000000000000000000000000 !
b11111000000100000110001100000000000000000000000000000 3
b11111000000100000110001100000000000000000000000000000 4
b11111000000100000110001100000000000000000000000000000 U
b100000000000000000000000000000000000000000000000000000 W
b100000000000000000000000000000000000000000000000000000 ]
b11111 \
b11111 c
b11111 f
b11111000000100000110001100000000000000000000000000000 S
b11111000000100000110001100000000000000000000000000000 a
b11111000000100000110001100000000000000000000000000000 T
b11111000000100000110001100000000000000000000000000000 b
1Z
b0 [
b0 d
b0 e
b0 X
b0 `
b110000000000000000000000000000000000000000000000000000 V
b110000000000000000000000000000000000000000000000000000 ^
1$
#560
0$
#570
b0 W
b0 ]
b111111111110000001000001100011 #
b111111111110000001000001100011 :
b11110 \
b11110 c
b11110 f
b111110000001000001100011000 D
b11110000001000001100011000 "
b11110000001000001100011000 /
b11110000001000001100011000 7
b11110000001000001100011000 J
b100000000000000000000000000000000000000000000000000000 V
b100000000000000000000000000000000000000000000000000000 ^
b11111 [
b11111 d
b11111 e
1$
#580
0$
#590
b11101 \
b11101 c
b11101 f
b11110 [
b11110 d
b11110 e
b0 V
b0 ^
1$
#600
0$
#610
b11100 \
b11100 c
b11100 f
b11101 [
b11101 d
b11101 e
1$
#620
0$
#630
b11011 \
b11011 c
b11011 f
b11100 [
b11100 d
b11100 e
1$
#640
0$
#650
b11010 \
b11010 c
b11010 f
b11011 [
b11011 d
b11011 e
1$
#660
0$
#670
b11001 \
b11001 c
b11001 f
b11010 [
b11010 d
b11010 e
1$
#680
0$
#690
b11000 \
b11000 c
b11000 f
b11001 [
b11001 d
b11001 e
1$
#700
0$
#710
b10111 \
b10111 c
b10111 f
b11000 [
b11000 d
b11000 e
1$
#720
0$
#730
b10110 \
b10110 c
b10110 f
b10111 [
b10111 d
b10111 e
1$
#740
0$
#750
b10101 \
b10101 c
b10101 f
b10110 [
b10110 d
b10110 e
1$
#760
0$
#770
b10100 \
b10100 c
b10100 f
b10101 [
b10101 d
b10101 e
1$
#780
0$
#790
b10011 \
b10011 c
b10011 f
b10100 [
b10100 d
b10100 e
1$
#800
0$
#810
b10010 \
b10010 c
b10010 f
b10011 [
b10011 d
b10011 e
1$
#820
0$
#830
b10001 \
b10001 c
b10001 f
b10010 [
b10010 d
b10010 e
1$
#840
0$
#850
b10000 \
b10000 c
b10000 f
b10001 [
b10001 d
b10001 e
1$
#860
0$
#870
b1111 \
b1111 c
b1111 f
b10000 [
b10000 d
b10000 e
1$
#880
0$
#890
b1110 \
b1110 c
b1110 f
b1111 [
b1111 d
b1111 e
1$
#900
0$
#910
b1101 \
b1101 c
b1101 f
b1110 [
b1110 d
b1110 e
1$
#920
0$
#930
b1100 \
b1100 c
b1100 f
b1101 [
b1101 d
b1101 e
1$
#940
0$
#950
b1011 \
b1011 c
b1011 f
b1100 [
b1100 d
b1100 e
1$
#960
0$
#970
b1010 \
b1010 c
b1010 f
b1011 [
b1011 d
b1011 e
1$
#980
0$
#990
b1001 \
b1001 c
b1001 f
b1010 [
b1010 d
b1010 e
1$
#1000
0$
#1010
b1000 \
b1000 c
b1000 f
b1001 [
b1001 d
b1001 e
1$
