aula3demaio/Dataflow.v
module adder (a,b,sinal, soma);

input signed [63:0] a, b;
output signed [63:0] soma;
input sinal;


assign soma = (sinal == 1'b0) ? (a + b):(a-b);
            
endmodule

module memoria(ads, clk, we, din, dout);
  
input [63 :0] ads;
input clk;
input we;
input signed [63:0] din;
output reg signed [63:0] dout;
reg signed [63:0] registradores [31:0]; // Registradores

initial begin
   
    registradores[0] = 45;
    registradores[1] = 11;
    
end

always@(posedge clk) begin

    $display("Registrador da memoria que recebe STORE         :", registradores[2]); 

    if (we)
        begin
          registradores[ads] <= din; // Escreve na memoria
        end
    else 
        begin
            dout <= registradores[ads]; // Lê a memoria
        end
end


endmodule

module registrador (clk, din, we, Rw, Ra, Rb, doutA, doutB);
    input clk;             // Clock do sistema
    input signed [63:0] din; // Dados de entrada  
    input we;          // Sinal de carregamento de dados
    output reg signed [64-1:0] doutA; 
    output reg signed [64-1:0]  doutB; // Dados de saída
    input [63:0] Rw;
    input [63:0] Ra;
    input [63:0] Rb;

    reg signed [63:0] registradores [31:0]; //Registradores

    initial begin
        
        registradores[0] = 0;
        registradores[1] = 1;
        registradores[5] = 2;
        registradores[6] = 36;

    end

    always @(posedge clk) begin

        $display("Registrador do banco onde ocorre o primeiro LOAD:", registradores[1]); 
        $display("Registrador do banco onde ocorre o segundo LOAD :", registradores[2]); 
        $display("Registrador do banco onde ocorre o primeiro ADD :", registradores[3]); 
        $display("Registrador do banco onde ocorre o primeiro SUB :", registradores[4]); 
        
        

        if (we) begin // Se o sinal de carregamento de dados estiver ativo
            registradores[Rw] <= din; // Carrega os dados de entrada no registrador
          
    
        end
        begin
            doutA <= registradores[Ra]; // Lê os dados do registrador 
            doutB <= registradores[Rb]; // Lê os dados do registrador 

    end
    end

    

endmodule

module Mux1 (C,Rb,sinalMux,S1 );

input signed [63:0] C, Rb;
output signed [63:0] S1;
input sinalMux;


assign S1 = (sinalMux == 1'b0) ? C: Rb;
            
endmodule


module Mux2 (dout, soma ,sinalMux, S2);

input signed [63:0] dout, soma;
output signed [63:0] S2;
input sinalMux;


assign S2 = (sinalMux == 1'b0) ? (dout):(soma);
            
endmodule

aula3demaio/testbench.v
`timescale 1ns/1ns

module testbench;

    // Inputs
    reg clock_tb;
    reg sinal_tb;
    wire signed [63:0] res_tb;
    wire [63:0] doutMem_tb;
    reg weReg_tb;
    reg [63:0] Rw_tb;
    reg [63:0] Ra_tb, Rb_tb;
    wire signed [63:0] doutA_tb;
    wire signed [63:0] doutB_tb;
    wire signed [63:0] S1_tb;
    wire signed [63:0] S2_tb;
    reg weMem_tb;
    reg sinalMux_tb;
    reg signed [63:0] C_tb;

    adder uut (
        .a(S1_tb), 
        .b(doutA_tb), 
        .soma(res_tb),
        .sinal(sinal_tb)
    );

    registrador utt (

        .clk(clock_tb),
        .din(S2_tb),
        .we(weReg_tb),
        .Rw(Rw_tb),
        .Ra(Ra_tb),
        .Rb(Rb_tb),
        .doutA(doutA_tb),
        .doutB(doutB_tb)
    );

    memoria utu (

        .clk(clock_tb),
        .ads(res_tb),
        .we(weMem_tb),
        .din(doutB_tb),
        .dout(doutMem_tb)
    );

    Mux1 utv (
        .C(C_tb),
        .Rb(doutB_tb),
        .sinalMux(sinalMux_tb),
        .S1(S1_tb)
    );

    Mux2 uvv (
        .dout(doutMem_tb),
        .soma(res_tb),
        .sinalMux(sinalMux_tb),
        .S2(S2_tb)
    );

    initial $dumpfile("testbench.vcd");
    initial $dumpvars(0, testbench);

    initial 
    begin
         //Para simular, precisa-se dar o sinal de clock(que será 0 ou 1), também o sinal do somador(0 se for soma ou 1 se for subtração),
        //Ainda, deve-se fornecer o b_tb que é endereço que será somado com zero(a_tb), e que será o endereço da memória. Por fim, também
        //é necessário fornecer o rw_tb que irá como endereço do registrador no momento do load, e também fornecer o ra_tb que será o endereço
        //onde a informação será lida no registrador. Por fim, é necessário fornecer o we do registrador(weReg_tb) e o we da memória(weReg_tb).
        //*******************************Abaixo é a simulação de dois loads no registrador: ********************************************************************
    
    
        clock_tb = 0;
        sinal_tb=0;
        Rw_tb = 1;
        Ra_tb= 0;
        C_tb = 0;
        sinalMux_tb = 0;
        #10
        #10   
        #10

        weReg_tb=1;
        #10
        
        #10
    
        Rw_tb = 2;
        Ra_tb = 0;
        C_tb = 1;
        sinalMux_tb = 0;
        #10
        #10
        #10
      
        // Add -- adicionando o que estava no reg[1] e reg[2] do banco e guardando no reg[3]
        
        Ra_tb = 2;
        Rb_tb = 1;
        Rw_tb = 3;
        sinalMux_tb =1;
        
        #10
        
        #10
        weReg_tb = 1;
        #10
        weReg_tb = 0;
        //Sub
        Ra_tb = 3;
        Rb_tb = 1;
        Rw_tb = 4;
        sinal_tb = 1;

        #10
        weReg_tb = 1;


      

//*******************************Abaixo é a simulação do store na memória: ********************************************************************
        #10
        Ra_tb = 5;
        Rb_tb = 6;
        weReg_tb = 0;
        sinal_tb = 0;
        sinalMux_tb =0;
        C_tb = 0;
        
        #10
        
        weMem_tb=1;

        #10
        
        #10
        weMem_tb=0;
        #10

        // Add

        Ra_tb = 2;
        Rb_tb = 1;
        Rw_tb = 3;
        sinalMux_tb =1;
        #10
        #10
        weReg_tb = 1;
        #10
        //Sub
        Ra_tb = 3;
        Rb_tb = 1;
        Rw_tb = 4;
        sinal_tb = 1;
        #10
        #10
        weReg_tb = 1;






       
$finish;

     
    end

        always #1 clock_tb = ~clock_tb;
    
    



endmodule

aula3demaio/testbench.vcd
$date
	Wed May  3 11:38:28 2023
$end
$version
	Icarus Verilog
$end
$timescale
	1ns
$end
$scope module testbench $end
$var wire 64 ! res_tb [63:0] $end
$var wire 64 " doutMem_tb [63:0] $end
$var wire 64 # doutB_tb [63:0] $end
$var wire 64 $ doutA_tb [63:0] $end
$var wire 64 % S2_tb [63:0] $end
$var wire 64 & S1_tb [63:0] $end
$var reg 64 ' C_tb [63:0] $end
$var reg 64 ( Ra_tb [63:0] $end
$var reg 64 ) Rb_tb [63:0] $end
$var reg 64 * Rw_tb [63:0] $end
$var reg 1 + clock_tb $end
$var reg 1 , sinalMux_tb $end
$var reg 1 - sinal_tb $end
$var reg 1 . weMem_tb $end
$var reg 1 / weReg_tb $end
$scope module utt $end
$var wire 64 0 Ra [63:0] $end
$var wire 64 1 Rb [63:0] $end
$var wire 64 2 Rw [63:0] $end
$var wire 1 + clk $end
$var wire 1 / we $end
$var wire 64 3 din [63:0] $end
$var reg 64 4 doutA [63:0] $end
$var reg 64 5 doutB [63:0] $end
$upscope $end
$scope module utu $end
$var wire 1 + clk $end
$var wire 64 6 din [63:0] $end
$var wire 1 . we $end
$var wire 64 7 ads [63:0] $end
$var reg 64 8 dout [63:0] $end
$upscope $end
$scope module utv $end
$var wire 64 9 C [63:0] $end
$var wire 64 : Rb [63:0] $end
$var wire 1 , sinalMux $end
$var wire 64 ; S1 [63:0] $end
$upscope $end
$scope module uut $end
$var wire 64 < a [63:0] $end
$var wire 64 = b [63:0] $end
$var wire 1 - sinal $end
$var wire 64 > soma [63:0] $end
$upscope $end
$scope module uvv $end
$var wire 64 ? dout [63:0] $end
$var wire 1 , sinalMux $end
$var wire 64 @ soma [63:0] $end
$var wire 64 A S2 [63:0] $end
$upscope $end
$upscope $end
$enddefinitions $end
#0
$dumpvars
bx A
bx @
bx ?
bx >
bx =
b0 <
b0 ;
bx :
b0 9
bx 8
bx 7
bx 6
bx 5
bx 4
bx 3
b1 2
bx 1
b0 0
x/
x.
0-
0,
0+
b1 *
bx )
b0 (
b0 '
b0 &
bx %
bx $
bx #
bx "
bx !
$end
#1
b0 !
b0 7
b0 >
b0 @
b0 $
b0 4
b0 =
1+
#2
0+
#3
b101101 %
b101101 3
b101101 A
b101101 "
b101101 8
b101101 ?
1+
#4
0+
#5
1+
#6
0+
#7
1+
#8
0+
#9
1+
#10
0+
#11
1+
#12
0+
#13
1+
#14
0+
#15
1+
#16
0+
#17
1+
#18
0+
#19
1+
#20
0+
#21
1+
#22
0+
#23
1+
#24
0+
#25
1+
#26
0+
#27
1+
#28
0+
#29
1+
#30
0+
1/
#31
1+
#32
0+
#33
1+
#34
0+
#35
1+
#36
0+
#37
1+
#38
0+
#39
1+
#40
0+
#41
1+
#42
0+
#43
1+
#44
0+
#45
1+
#46
0+
#47
1+
#48
0+
#49
1+
#50
b1 !
b1 7
b1 >
b1 @
b1 &
b1 ;
b1 <
0+
b1 '
b1 9
b10 *
b10 2
#51
b1011 %
b1011 3
b1011 A
b1011 "
b1011 8
b1011 ?
1+
#52
0+
#53
1+
#54
0+
#55
1+
#56
0+
#57
1+
#58
0+
#59
1+
#60
0+
#61
1+
#62
0+
#63
1+
#64
0+
#65
1+
#66
0+
#67
1+
#68
0+
#69
1+
#70
0+
#71
1+
#72
0+
#73
1+
#74
0+
#75
1+
#76
0+
#77
1+
#78
0+
#79
1+
#80
bx !
bx 7
bx >
bx @
bx &
bx ;
bx <
bx %
bx 3
bx A
0+
1,
b11 *
b11 2
b1 )
b1 1
b10 (
b10 0
#81
b111000 %
b111000 3
b111000 A
b111000 !
b111000 7
b111000 >
b111000 @
b101101 &
b101101 ;
b101101 <
b101101 #
b101101 5
b101101 6
b101101 :
b1011 $
b1011 4
b1011 =
bx "
bx 8
bx ?
1+
#82
0+
#83
1+
#84
0+
#85
1+
#86
0+
#87
1+
#88
0+
#89
1+
#90
0+
#91
1+
#92
0+
#93
1+
#94
0+
#95
1+
#96
0+
#97
1+
#98
0+
#99
1+
#100
0+
#101
1+
#102
0+
#103
1+
#104
0+
#105
1+
#106
0+
#107
1+
#108
0+
#109
1+
#110
b100010 %
b100010 3
b100010 A
b100010 !
b100010 7
b100010 >
b100010 @
0+
1-
b100 *
b100 2
b11 (
b11 0
0/
#111
b1111111111111111111111111111111111111111111111111111111111110101 %
b1111111111111111111111111111111111111111111111111111111111110101 3
b1111111111111111111111111111111111111111111111111111111111110101 A
b1111111111111111111111111111111111111111111111111111111111110101 !
b1111111111111111111111111111111111111111111111111111111111110101 7
b1111111111111111111111111111111111111111111111111111111111110101 >
b1111111111111111111111111111111111111111111111111111111111110101 @
b111000 $
b111000 4
b111000 =
1+
#112
0+
#113
1+
#114
0+
#115
1+
#116
0+
#117
1+
#118
0+
#119
1+
#120
0+
1/
#121
1+
#122
0+
#123
1+
#124
0+
#125
1+
#126
0+
#127
1+
#128
0+
#129
1+
#130
b0 &
b0 ;
b0 <
bx %
bx 3
bx A
b111000 !
b111000 7
b111000 >
b111000 @
0+
b0 '
b0 9
0,
0-
0/
b110 )
b110 1
b101 (
b101 0
#131
b10 !
b10 7
b10 >
b10 @
b100100 #
b100100 5
b100100 6
b100100 :
b10 $
b10 4
b10 =
1+
#132
0+
#133
1+
#134
0+
#135
1+
#136
0+
#137
1+
#138
0+
#139
1+
#140
0+
1.
#141
1+
#142
0+
#143
1+
#144
0+
#145
1+
#146
0+
#147
1+
#148
0+
#149
1+
#150
0+
#151
1+
#152
0+
#153
1+
#154
0+
#155
1+
#156
0+
#157
1+
#158
0+
#159
1+
#160
0+
0.
#161
b100100 %
b100100 3
b100100 A
b100100 "
b100100 8
b100100 ?
1+
#162
0+
#163
1+
#164
0+
#165
1+
#166
0+
#167
1+
#168
0+
#169
1+
#170
b100110 !
b100110 7
b100110 >
b100110 @
b100100 &
b100100 ;
b100100 <
b100110 %
b100110 3
b100110 A
0+
1,
b11 *
b11 2
b1 )
b1 1
b10 (
b10 0
#171
b111000 %
b111000 3
b111000 A
b101101 &
b101101 ;
b101101 <
b111000 !
b111000 7
b111000 >
b111000 @
bx "
bx 8
bx ?
b101101 #
b101101 5
b101101 6
b101101 :
b1011 $
b1011 4
b1011 =
1+
#172
0+
#173
1+
#174
0+
#175
1+
#176
0+
#177
1+
#178
0+
#179
1+
#180
0+
#181
1+
#182
0+
#183
1+
#184
0+
#185
1+
#186
0+
#187
1+
#188
0+
#189
1+
#190
0+
1/
#191
1+
#192
0+
#193
1+
#194
0+
#195
1+
#196
0+
#197
1+
#198
0+
#199
1+
#200
b100010 %
b100010 3
b100010 A
b100010 !
b100010 7
b100010 >
b100010 @
0+
1-
b100 *
b100 2
b11 (
b11 0
#201
b1111111111111111111111111111111111111111111111111111111111110101 %
b1111111111111111111111111111111111111111111111111111111111110101 3
b1111111111111111111111111111111111111111111111111111111111110101 A
b1111111111111111111111111111111111111111111111111111111111110101 !
b1111111111111111111111111111111111111111111111111111111111110101 7
b1111111111111111111111111111111111111111111111111111111111110101 >
b1111111111111111111111111111111111111111111111111111111111110101 @
b111000 $
b111000 4
b111000 =
1+
