floatingpoint-COMBINED/fd.v
module fd(clock, operando_a, op, reset, operando_b, sinalMuxFP1, sinalMuxFP2, sinalMuxFP3, sinalMuxFP4, sinalMuxFP5, sinalShiftFract, sinalShiftRes, sinalIncOrDec, sinalRound, exp_dif, ula, round_fract, resultado);

input [31:0] operando_a, operando_b;
input sinalMuxFP1, sinalMuxFP2, sinalMuxFP3, sinalMuxFP4, sinalMuxFP5;
input [7:0] sinalShiftFract;
input [8:0] sinalShiftRes;
input clock;
input [1:0] op;
input [8:0] sinalIncOrDec;
input sinalRound;
output [31:0] resultado;
output [7:0] exp_dif;
output [26:0] ula;
input reset;
output [25:0] round_fract;


wire [7:0] ula_exp_out;
wire [7:0] reg_exp_out;
wire [7:0] mux1_out;
wire [27:0] mux2_out;
wire [24:0] mux3_out;
wire [27:0] shift_right_out;
wire [27:0] ula_out;
wire [25:0] round_fract_out;
wire [7:0] round_exp_out;
wire [7:0] mux4_out;
wire [27:0] mux5_out;
wire [7:0] ula_exp_one_out;
wire [27:0] shift_res_out;
wire [7:0] exp_op;

assign exp_dif = reg_exp_out; // Saida do registrador da diferença de expoente
assign ula = ula_out; // Saida da ula
assign round_fract = round_fract_out;
assign resultado = {shift_res_out[27], round_exp_out, round_fract_out[25:3]};

ULA_exp ula_exp(
    .a(operando_a[30:23]),
    .b(operando_b[30:23]),
    .exp_final(ula_exp_out),
    .op(op)
);

registrador registrador(
    .data_in(ula_exp_out),
    .data_out(reg_exp_out),
    .clock(clock)
);


MuxFP1 mux_fp1(
    .exp1(operando_a[30:23]),
    .exp2(operando_b[30:23]),
    .sinalMuxFP1(sinalMuxFP1), // dont care para a mult
    .greatestExp(mux1_out)
);

MuxFP2 mux_fp2(
    .fraction1({operando_a[31], 1'b1, operando_a[22:0]}),
    .fraction2({operando_b[31], 1'b1, operando_b[22:0]}), // dont care para mult
    .sinalMuxFP2(sinalMuxFP2),
    .biggerNumber(mux2_out)
);

MuxFP3 mux_fp3(
    .fraction1({operando_a[31], 1'b1, operando_a[22:0]}),
    .fraction2({operando_b[31], 1'b1, operando_b[22:0]}), // dont care para mult
    .sinalMuxFP3(sinalMuxFP3),
    .smallerNumber(mux3_out)
);

shift_fraction shift_fraction(
    .b(mux3_out),
    .sinal(sinalShiftFract),
    .op(op), // nao faz nada na mult
    .b_out(shift_right_out)
);

ULA_Float ula_float(
    .b(shift_right_out), 
    .a(mux2_out), 
    .resultado(ula_out), 
    .reset(reset), 
    .clock(clock), 
    .op(op)
    );

MuxFP5 mux_fp5 (
    .fraction1(ula_out),
    .fraction2({shift_res_out[27], 1'b1, round_fract}),
    .sinalMuxFP5(sinalMuxFP5),
    .fraction(mux5_out)
);

MuxFP4 mux_fp4 (
    .exp1(exp_op),
    .exp2(round_exp_out),
    .sinalMuxFP4(sinalMuxFP4),
    .exp(mux4_out)

);

ULA_exp_one ula_exp_one (
    .b(mux4_out),
    .sinal(sinalIncOrDec),
    .res(ula_exp_one_out)

);

shift_res shift_res (
    .b(mux5_out),
    .sinal(sinalShiftRes),
    .res(shift_res_out)
);

MuxFP6 mux_fp6(
    .exp_soma(mux1_out),
    .exp_mult(ula_exp_out),
    .op(op),
    .exp_op(exp_op)
);

round round (
    .exp_inicial(ula_exp_one_out),
    .fract_inicial(shift_res_out[26:1]),
    .clock(clock),
    .sinal(sinalRound),
    .exp_final(round_exp_out),
    .fract_final(round_fract_out)
);


endmodule

module round(exp_inicial, fract_inicial, exp_final, fract_final, sinal, clock);

input clock;
input [7:0] exp_inicial;
output reg [7:0] exp_final;
input [25:0] fract_inicial;
output reg [25:0] fract_final;
wire [25:0] arredondado;
input sinal;

assign arredondado = (fract_inicial[2:0] == 3'b111) ? ({fract_inicial[25:3]+1'b1, 3'b000}):
                           (fract_inicial[2:0] == 3'b101) ? ({fract_inicial[25:3]+1'b1, 3'b000}):
                           (fract_inicial[2:0] == 3'b110) ? ({fract_inicial[25:3]+1'b1, 3'b000}):
                           (fract_inicial[2:0] == 3'b100 && fract_inicial[3]==1'b1) ? ({fract_inicial[25:3]+1'b1, 3'b000}):
                            {fract_inicial[25:3], 3'b000};

always @(posedge clock)
begin   
    if(sinal) begin
        fract_final <= arredondado; 
    end
    else begin
        fract_final <= fract_inicial;
    end
    exp_final <= exp_inicial;

end
                           
endmodule

module registrador(clock, data_in, data_out);

input             clock;
input      [7:0] data_in;
output  reg   [7:0] data_out;


always @(posedge clock)
begin
        data_out <= data_in[7:0]; 

end

endmodule

module ULA_exp (b, a, op, exp_final);

input [7:0] b, a; 
input [1:0] op;
wire [7:0] sub;
wire [7:0] soma_exp;
output [7:0] exp_final;

assign sub = (a>b) ? (a - b): (b - a);
assign soma_exp = (a-127) + (b-127) + 2'b10; 
assign exp_final  = (op == 2'b00) ? sub: soma_exp;
     
endmodule

module shift_fraction(b, sinal, b_out, op);

input [24:0] b;
input [1:0] op;
input [7:0] sinal; //quanto shiftar
wire [27:0] res;
output [27:0] b_out;

assign res = (sinal[7:0] == 0) ? {b[24], b[23:0] >> sinal[7:0], 3'b000}:
             (sinal[7:0] == 1) ? {b[24], b[23:0] >> sinal[7:0], b[sinal-1], 2'b00}:
             (sinal[7:0] == 2) ? {b[24], b[23:0] >> sinal[7:0], b[sinal-1], b[sinal-2], 1'b0}:
             {b[24], b[23:0] >> sinal[7:0], b[sinal-1], b[sinal-2], b[sinal-3]};
assign b_out = (op == 2'b00) ? res: {b,3'b000};


endmodule

module shift_res(b, sinal, res);

input [27:0] b;
input [8:0] sinal;  
output [27:0] res;

assign res = (sinal[8] == 1)? {b[27], b[26:0] << sinal[7:0]}:
                            {b[27], b[26:0] >> sinal[7:0]};

endmodule

module ULA_exp_one (b, sinal, res);

input [7:0] b; 
input [8:0] sinal;
output [7:0] res;

assign res = (sinal[8] == 1'b0) ? (b+sinal[7:0]):
                                  (b-sinal[7:0]); 
     
endmodule

module MuxFP1 (exp1, exp2, sinalMuxFP1, greatestExp);

input [7:0] exp1;
input [7:0] exp2;
output [7:0] greatestExp; // Vai para MuxFP6
input sinalMuxFP1;

assign greatestExp = (sinalMuxFP1 == 1'b0) ? (exp1 + 1'b1) : (exp2 + 1'b1); // adicionando um bit ao expoente pois colocamos o 1 implicito para fazer as contas

endmodule

module MuxFP6 (exp_soma, exp_mult, op, exp_op);

input [7:0] exp_soma;
input [7:0] exp_mult;
output [7:0] exp_op; // Vai para MuxFP4
input [1:0] op;

assign exp_op = (op == 2'b00) ? (exp_soma) : exp_mult;

endmodule

module MuxFP2 (fraction1, fraction2, sinalMuxFP2, biggerNumber);

input [24:0] fraction1;
input [24:0] fraction2;
output [27:0] biggerNumber; // Vai receber shift para a direita e ir pra ULA grande
input sinalMuxFP2;

assign biggerNumber = (sinalMuxFP2 == 1'b0) ? {(fraction1),3'b000}  : {(fraction2), 3'b000};

endmodule

module MuxFP3 (fraction1, fraction2, sinalMuxFP3, smallerNumber);

input [24:0] fraction1;
input [24:0] fraction2;
output [24:0] smallerNumber; // Vai para ULA grande
input sinalMuxFP3;

assign smallerNumber = (sinalMuxFP3 == 1'b0) ? (fraction1) : (fraction2);

endmodule

module MuxFP4 (exp1, exp2, sinalMuxFP4, exp);

input [7:0] exp1;
input [7:0] exp2;
output [7:0] exp; // Será incrementado ou decrementado
input sinalMuxFP4;

assign exp = (sinalMuxFP4 == 1'b0) ? (exp1) : (exp2);

endmodule

module MuxFP5 (fraction1, fraction2, sinalMuxFP5, fraction);

input [27:0] fraction1;
input [27:0] fraction2;
output [27:0] fraction; // receberá shift para a direita ou esquerda
input sinalMuxFP5;

assign fraction = (sinalMuxFP5 == 1'b0) ? (fraction1) : (fraction2);

endmodule


// MULT

module ULA_Float(a, b, resultado, reset, clock, op); // Multiplicação

input [27:0] b, a; // Mantissa e o bit de sinal
input [1:0] op; // 00 - SOMA, 01 - MULT
wire [26:0] soma; 
wire overflow;
wire sinal;
wire [27:0] add;

assign {sinal, overflow, soma} = (a[27]|b[27] == 1'b0) ? {1'b0,(a+b)} : // OR com os bits de sinal para verificar se os dois são positivos
              (a[27] == 1'b1 && (a[26:0] > b[26:0])) ? {1'b1,(a-b)}:
              (b[27] == 1'b1 && (b[26:0] > a[26:0])) ? {1'b1,(b-a)}:
              (a[27] == 1'b1 && (a[26:0] < b[26:0])) ? {1'b0,(b-a)}:
              (b[27] == 1'b1 && (b[26:0] < a[26:0])) ? {1'b0,(a-b)}:
              {1'b0, (a+b)};

assign add = {sinal, soma};

wire [27:0] multiplicador;
wire [27:0] multiplicando;
input reset;
input clock;
wire [53:0] produto;
output [27:0] resultado;

wire [54:0] produto_in;
wire [54:0] produto_out;
wire [54:0] produto_soma;
wire [26:0] multiplicador_shift_in;
wire [26:0] multiplicador_shift_out;
wire [53:0] multiplicando_shift_in;
wire [53:0] multiplicando_shift_out;
wire [54:0] produto_shift;
wire [4:0] N_out;
wire [4:0] N_in;
wire done;

registrador_soma regA (
    .reset(reset),
    .clock(clock),
    .data_in(produto_soma),
    .data_out(produto_out)
);

registrador_N reg_N (
    .reset(reset),
    .clock(clock),
    .data_out(N_out),
    .data_in(N_in),
    .done(done)
);

subtracao sub(
    .N(N_out),
    .reset(reset),
    .sub(N_in)
);

registrador_multiplicador multR(
    .data_in(multiplicador_shift_in),
    .data_out(multiplicador_shift_out),
    .clock(clock),
    .reset(reset)
);

registrador_multiplicando multD(
    .data_in(multiplicando_shift_in),
    .data_out(multiplicando_shift_out),
    .clock(clock),
    .reset(reset)
);

assign multiplicador = a;
assign multiplicando = b;
assign multiplicador_shift_in = (reset) ? multiplicador[26:0]: multiplicador_shift_out >> 1; //Shift do multiplicador
assign multiplicando_shift_in = (reset) ? {27'b0, multiplicando[26:0]}: multiplicando_shift_out << 1; // Shift do multiplicando
assign produto_soma = (multiplicador_shift_out[0] == 1) ? (produto_out + multiplicando_shift_out): produto_out; // Soma
assign produto = (done) ? produto_soma: 9'bz; // Produto final

assign resultado = (op == 2'b00) ? add: {a[27]^b[27],produto[53:27]};

endmodule

module registrador_multiplicador(data_in, data_out, clock, reset);

input             clock;
input      [26:0] data_in;
input               reset;
output  reg   [26:0] data_out;

always @(posedge clock or posedge reset)
begin   
            data_out <= data_in; 

end
endmodule

module registrador_multiplicando(data_in, data_out, clock, reset);

input             clock;
input      [53:0] data_in;
input               reset;
output  reg   [53:0] data_out;

always @(posedge clock or posedge reset)
begin   
            data_out <= data_in; 

end
endmodule

module registrador_soma(clock, data_in, data_out, reset);

input             clock;
input      [54:0] data_in;
input               reset;
output  reg   [54:0] data_out;

always @(posedge clock or posedge reset)
begin   
        if(reset) 
            data_out <=0;
        else 
            data_out <= data_in[54:0]; 

end
endmodule

module subtracao(N, sub, reset);

input [4:0]  N;
input reset;
output [4:0] sub;

assign sub = (~reset) ? N - 1 : N;

endmodule

module registrador_N(clock, data_out, data_in, reset, done);

input             clock;
input               reset;
output  reg   [4:0] data_out;
input           [4:0] data_in;
output   reg          done;

always @(posedge clock or posedge reset)
begin   
        if(reset) begin
            done <=0;
            data_out <= 5'b11011;
        end
        else 
            data_out <= data_in[4:0]; 
            if(data_in == 0)
                done <= 1;

end
endmodule

floatingpoint-COMBINED/tb.v
// **********GRUPO ************
// Helena Bianchi Moyen
// Luiz Mariano
// Mariana Watanabe


`timescale 1ns/1ns

module testbench;

    reg [31:0] operando_a_tb, operando_b_tb;
    reg sinalMuxFP1_tb, sinalMuxFP2_tb, sinalMuxFP3_tb, sinalMuxFP4_tb, sinalMuxFP5_tb;
    reg [7:0] sinalShiftFract_tb;
    reg [8:0] sinalShiftRes_tb;
    reg [8:0] sinalIncOrDec_tb;
    reg sinalRound_tb;
    reg clock_tb;
    reg [1:0] op_tb;
    reg reset_tb;

    wire [31:0] resultado_tb;
    wire [7:0] exp_dif_tb;
    wire [26:0] ula_tb;
    wire [25:0] round_fract_tb;

    fd fd(
        .clock(clock_tb), 
        .op(op_tb),
        .operando_a(operando_a_tb), 
        .operando_b(operando_b_tb),
        .sinalMuxFP1(sinalMuxFP1_tb), 
        .sinalMuxFP2(sinalMuxFP2_tb), 
        .sinalMuxFP4(sinalMuxFP4_tb),
        .sinalMuxFP3(sinalMuxFP3_tb), 
        .sinalMuxFP5(sinalMuxFP5_tb), 
        .sinalShiftFract(sinalShiftFract_tb), 
        .sinalShiftRes(sinalShiftRes_tb), 
        .sinalIncOrDec(sinalIncOrDec_tb), 
        .sinalRound(sinalRound_tb), 
        .exp_dif(exp_dif_tb), 
        .ula(ula_tb), 
        .reset(reset_tb),
        .round_fract(round_fract_tb), 
        .resultado(resultado_tb)
    );

    initial $dumpfile("testbench.vcd");
    initial $dumpvars(0, testbench);

    initial 
    begin
        
        //*******************************Abaixo é a simulação: ********************************************************************
        clock_tb =0;
        op_tb = 2'b00;
        operando_a_tb = 32'b00111111110000000000000000000000; // 1,5
        operando_b_tb = 32'b00111111000000000000000000000000; // 0,5
        sinalMuxFP1_tb = 0; // exp de 0,5 eh menor que de 1,5
        sinalMuxFP2_tb = 0; // a > b
        sinalMuxFP3_tb = 1; // b < a
        sinalMuxFP5_tb = 0;
        sinalShiftFract_tb = 1; // shift de b em 1
        sinalShiftRes_tb  = 9'b100000000; // nao precisamos shiftar nada (mantissa eh 0)
        sinalIncOrDec_tb  = 9'b000000000; // 
        sinalMuxFP4_tb = 0;
        sinalRound_tb = 0;
        // esperado: 01000000000000000000000000000000 =
        #50
        $display("Resultado de 1,5 + 0,5: %b", resultado_tb);
        op_tb = 2'b00;
        operando_a_tb = 32'b00111111101000100100110111010011; // 1,268
        operando_b_tb = 32'b01000000000111010010111100011011; // 2,456
        // esperado : 01000000011011100101011000000100 = 3,724
        sinalMuxFP1_tb = 1; // exp de 1,268 eh menor que de 2,456
        sinalMuxFP2_tb = 1; // b > a (em modulo)
        sinalMuxFP3_tb = 0; // a < b (eme modulo)
        sinalMuxFP5_tb = 0;
        sinalShiftFract_tb = 1; // shift de a em 1
        sinalShiftRes_tb  = 9'b100000001; // shift de um para esquerda 
        sinalIncOrDec_tb  = 9'b100000001; // decrementa 1, pois shiftamos uma vez para a esquerda
        sinalMuxFP4_tb = 0;
        sinalRound_tb = 0;
        #100
        $display("Resultado de 1,268 + 2,456 %b", resultado_tb);
        op_tb = 2'b00;
        operando_a_tb = 32'b10111111101000100100110111010011; // -1,268
        operando_b_tb = 32'b01000000000111010010111100011011; // 2,456
        // esperado : 00111111100110000001000001100011 = 1,188000
         //           00111111100110000001000001100011
        sinalMuxFP1_tb = 1; // exp de 1,268 eh menor que de 2,456
        sinalMuxFP2_tb = 1; // b > a (em modulo)
        sinalMuxFP3_tb = 0; // a < b (em modulo)
        sinalMuxFP5_tb = 0;
        sinalShiftFract_tb = 1; // shift de a em 1
        sinalShiftRes_tb  = 9'b100000010; // shift de dois para esquerda 
        sinalIncOrDec_tb  = 9'b100000010; // decrementa 2, pois shiftamos duas vezes para a esquerda
        sinalMuxFP4_tb = 0;
        sinalRound_tb = 0;
        #100
        $display("Resultado de - 1,268 + 2,456 %b", resultado_tb);
        op_tb = 2'b00;
        operando_a_tb = 32'b01000001101001010101110000101001; // 20.6700000763
        operando_b_tb = 32'b00111111001010111000010100011111; // 0.670000016689
        // esperado : 01000001101010101011100001010010 = 21.3400001526
        sinalMuxFP1_tb = 0; // exp de 0.67 eh menor 
        sinalMuxFP2_tb = 0; // a > b
        sinalMuxFP3_tb = 1; // b < a
        sinalMuxFP5_tb = 0;
        sinalShiftFract_tb = 5; 
        sinalShiftRes_tb  = 9'b100000001; // shift de dois para esquerda 
        sinalIncOrDec_tb  = 9'b100000001; // decrementa 2, pois shiftamos duas vezes para a esquerda
        sinalMuxFP4_tb = 0;
        sinalRound_tb = 1; // Verifique no GTK Wave o arredondamento que o corre
        #100

        $display("Resultado de 20.67 + 0.67  %b", resultado_tb);
        clock_tb  = 0;
        #1
        reset_tb = 1;
        op_tb = 2'b10;
        operando_a_tb = 32'b00111111101001010110000001000010; //1.292
        operando_b_tb = 32'b00111111110000000000000000000000;//1.5
        sinalMuxFP1_tb = 0; // exp de 0.67 eh menor 
        sinalMuxFP2_tb = 0; // a > b
        sinalMuxFP3_tb = 1; // b < a
        sinalMuxFP4_tb = 0; 
        sinalMuxFP5_tb = 0;
        sinalShiftRes_tb  = 9'b100000010; // shift de dois para esquerda 
        sinalIncOrDec_tb  = 9'b100000010;
        #10
        reset_tb = 0;
        #1000
        $display("Fim da simulação: %b", resultado_tb);
        $finish;

        $display("Fim da simulação");
        $finish;

     
    end

        always #10 clock_tb = ~clock_tb;
    
    

endmodule

floatingpoint-COMBINED/testbench.vcd
$date
	Mon Jun 26 10:53:24 2023
$end
$version
	Icarus Verilog
$end
$timescale
	1ns
$end
$scope module testbench $end
$var wire 27 ! ula_tb [26:0] $end
$var wire 26 " round_fract_tb [25:0] $end
$var wire 32 # resultado_tb [31:0] $end
$var wire 8 $ exp_dif_tb [7:0] $end
$var reg 1 % clock_tb $end
$var reg 2 & op_tb [1:0] $end
$var reg 32 ' operando_a_tb [31:0] $end
$var reg 32 ( operando_b_tb [31:0] $end
$var reg 1 ) reset_tb $end
$var reg 9 * sinalIncOrDec_tb [8:0] $end
$var reg 1 + sinalMuxFP1_tb $end
$var reg 1 , sinalMuxFP2_tb $end
$var reg 1 - sinalMuxFP3_tb $end
$var reg 1 . sinalMuxFP4_tb $end
$var reg 1 / sinalMuxFP5_tb $end
$var reg 1 0 sinalRound_tb $end
$var reg 8 1 sinalShiftFract_tb [7:0] $end
$var reg 9 2 sinalShiftRes_tb [8:0] $end
$scope module fd $end
$var wire 1 % clock $end
$var wire 8 3 exp_dif [7:0] $end
$var wire 2 4 op [1:0] $end
$var wire 32 5 operando_a [31:0] $end
$var wire 32 6 operando_b [31:0] $end
$var wire 1 ) reset $end
$var wire 26 7 round_fract [25:0] $end
$var wire 9 8 sinalIncOrDec [8:0] $end
$var wire 1 + sinalMuxFP1 $end
$var wire 1 , sinalMuxFP2 $end
$var wire 1 - sinalMuxFP3 $end
$var wire 1 . sinalMuxFP4 $end
$var wire 1 / sinalMuxFP5 $end
$var wire 1 0 sinalRound $end
$var wire 8 9 sinalShiftFract [7:0] $end
$var wire 9 : sinalShiftRes [8:0] $end
$var wire 28 ; ula_out [27:0] $end
$var wire 8 < ula_exp_out [7:0] $end
$var wire 8 = ula_exp_one_out [7:0] $end
$var wire 27 > ula [26:0] $end
$var wire 28 ? shift_right_out [27:0] $end
$var wire 28 @ shift_res_out [27:0] $end
$var wire 26 A round_fract_out [25:0] $end
$var wire 8 B round_exp_out [7:0] $end
$var wire 32 C resultado [31:0] $end
$var wire 8 D reg_exp_out [7:0] $end
$var wire 28 E mux5_out [27:0] $end
$var wire 8 F mux4_out [7:0] $end
$var wire 25 G mux3_out [24:0] $end
$var wire 28 H mux2_out [27:0] $end
$var wire 8 I mux1_out [7:0] $end
$var wire 8 J exp_op [7:0] $end
$scope module mux_fp1 $end
$var wire 8 K exp1 [7:0] $end
$var wire 8 L exp2 [7:0] $end
$var wire 1 + sinalMuxFP1 $end
$var wire 8 M greatestExp [7:0] $end
$upscope $end
$scope module mux_fp2 $end
$var wire 25 N fraction1 [24:0] $end
$var wire 25 O fraction2 [24:0] $end
$var wire 1 , sinalMuxFP2 $end
$var wire 28 P biggerNumber [27:0] $end
$upscope $end
$scope module mux_fp3 $end
$var wire 25 Q fraction1 [24:0] $end
$var wire 25 R fraction2 [24:0] $end
$var wire 1 - sinalMuxFP3 $end
$var wire 25 S smallerNumber [24:0] $end
$upscope $end
$scope module mux_fp4 $end
$var wire 1 . sinalMuxFP4 $end
$var wire 8 T exp2 [7:0] $end
$var wire 8 U exp1 [7:0] $end
$var wire 8 V exp [7:0] $end
$upscope $end
$scope module mux_fp5 $end
$var wire 28 W fraction2 [27:0] $end
$var wire 1 / sinalMuxFP5 $end
$var wire 28 X fraction1 [27:0] $end
$var wire 28 Y fraction [27:0] $end
$upscope $end
$scope module mux_fp6 $end
$var wire 8 Z exp_soma [7:0] $end
$var wire 2 [ op [1:0] $end
$var wire 8 \ exp_op [7:0] $end
$var wire 8 ] exp_mult [7:0] $end
$upscope $end
$scope module registrador $end
$var wire 1 % clock $end
$var wire 8 ^ data_in [7:0] $end
$var reg 8 _ data_out [7:0] $end
$upscope $end
$scope module round $end
$var wire 1 % clock $end
$var wire 26 ` fract_inicial [25:0] $end
$var wire 1 0 sinal $end
$var wire 8 a exp_inicial [7:0] $end
$var wire 26 b arredondado [25:0] $end
$var reg 8 c exp_final [7:0] $end
$var reg 26 d fract_final [25:0] $end
$upscope $end
$scope module shift_fraction $end
$var wire 25 e b [24:0] $end
$var wire 2 f op [1:0] $end
$var wire 8 g sinal [7:0] $end
$var wire 28 h res [27:0] $end
$var wire 28 i b_out [27:0] $end
$upscope $end
$scope module shift_res $end
$var wire 28 j b [27:0] $end
$var wire 9 k sinal [8:0] $end
$var wire 28 l res [27:0] $end
$upscope $end
$scope module ula_exp $end
$var wire 8 m a [7:0] $end
$var wire 8 n b [7:0] $end
$var wire 2 o op [1:0] $end
$var wire 8 p sub [7:0] $end
$var wire 8 q soma_exp [7:0] $end
$var wire 8 r exp_final [7:0] $end
$upscope $end
$scope module ula_exp_one $end
$var wire 8 s b [7:0] $end
$var wire 9 t sinal [8:0] $end
$var wire 8 u res [7:0] $end
$upscope $end
$scope module ula_float $end
$var wire 28 v a [27:0] $end
$var wire 28 w b [27:0] $end
$var wire 1 % clock $end
$var wire 28 x multiplicador [27:0] $end
$var wire 28 y multiplicando [27:0] $end
$var wire 2 z op [1:0] $end
$var wire 1 ) reset $end
$var wire 27 { soma [26:0] $end
$var wire 1 | sinal $end
$var wire 28 } resultado [27:0] $end
$var wire 55 ~ produto_soma [54:0] $end
$var wire 55 !" produto_out [54:0] $end
$var wire 54 "" produto [53:0] $end
$var wire 1 #" overflow $end
$var wire 54 $" multiplicando_shift_out [53:0] $end
$var wire 54 %" multiplicando_shift_in [53:0] $end
$var wire 27 &" multiplicador_shift_out [26:0] $end
$var wire 27 '" multiplicador_shift_in [26:0] $end
$var wire 1 (" done $end
$var wire 28 )" add [27:0] $end
$var wire 5 *" N_out [4:0] $end
$var wire 5 +" N_in [4:0] $end
$scope module multD $end
$var wire 1 % clock $end
$var wire 54 ," data_in [53:0] $end
$var wire 1 ) reset $end
$var reg 54 -" data_out [53:0] $end
$upscope $end
$scope module multR $end
$var wire 1 % clock $end
$var wire 27 ." data_in [26:0] $end
$var wire 1 ) reset $end
$var reg 27 /" data_out [26:0] $end
$upscope $end
$scope module regA $end
$var wire 1 % clock $end
$var wire 55 0" data_in [54:0] $end
$var wire 1 ) reset $end
$var reg 55 1" data_out [54:0] $end
$upscope $end
$scope module reg_N $end
$var wire 1 % clock $end
$var wire 1 ) reset $end
$var wire 5 2" data_in [4:0] $end
$var reg 5 3" data_out [4:0] $end
$var reg 1 (" done $end
$upscope $end
$scope module sub $end
$var wire 5 4" N [4:0] $end
$var wire 1 ) reset $end
$var wire 5 5" sub [4:0] $end
$upscope $end
$upscope $end
$upscope $end
$upscope $end
$enddefinitions $end
#0
$dumpvars
bx 5"
bx 4"
bx 3"
bx 2"
bx 1"
bx 0"
bx /"
bx ."
bx -"
bx0 ,"
bx +"
bx *"
b0 )"
x("
bx '"
bx &"
bx0 %"
bx $"
1#"
bx ""
bx !"
bx ~
b0 }
0|
b0 {
b0 z
b10000000000000000000000000 y
b110000000000000000000000000 x
b10000000000000000000000000 w
b110000000000000000000000000 v
b10000000 u
b0 t
b10000000 s
b1 r
b1 q
b1 p
b0 o
b1111110 n
b1111111 m
b0 l
b100000000 k
b0 j
b10000000000000000000000000 i
b10000000000000000000000000 h
b1 g
b0 f
b100000000000000000000000 e
bx d
bx c
b0 b
b10000000 a
b0 `
bx _
b1 ^
b1 ]
b10000000 \
b0 [
b10000000 Z
b0 Y
b0 X
b1xxxxxxxxxxxxxxxxxxxxxxxxxx W
b10000000 V
b10000000 U
bx T
b100000000000000000000000 S
b100000000000000000000000 R
b110000000000000000000000 Q
b110000000000000000000000000 P
b100000000000000000000000 O
b110000000000000000000000 N
b10000000 M
b1111110 L
b1111111 K
b10000000 J
b10000000 I
b110000000000000000000000000 H
b100000000000000000000000 G
b10000000 F
b0 E
bx D
b0xxxxxxxxxxxxxxxxxxxxxxxxxxxxxxx C
bx B
bx A
b0 @
b10000000000000000000000000 ?
b0 >
b10000000 =
b1 <
b0 ;
b100000000 :
b1 9
b0 8
bx 7
b111111000000000000000000000000 6
b111111110000000000000000000000 5
b0 4
bx 3
b100000000 2
b1 1
00
0/
0.
1-
0,
0+
b0 *
x)
b111111000000000000000000000000 (
b111111110000000000000000000000 '
b0 &
0%
bx $
b0xxxxxxxxxxxxxxxxxxxxxxxxxxxxxxx #
bx "
b0 !
$end
#10
bx00 %"
bx00 ,"
b1 $
b1 3
b1 D
b1 _
b1000000000000000000000000000000 #
b1000000000000000000000000000000 C
b10000000 B
b10000000 T
b10000000 c
b100000000000000000000000000 W
b0 "
b0 7
b0 A
b0 d
bx0 $"
bx0 -"
1%
#20
0%
#30
bx000 %"
bx000 ,"
bx00 $"
bx00 -"
1%
#40
0%
#50
bx000 $"
bx000 -"
b11011100101011000000100000 b
b11011100101011000000100100 `
b110111001010110000001001000 @
b110111001010110000001001000 l
bx00 %"
bx00 ,"
b111011100101011000000100100 E
b111011100101011000000100100 Y
b111011100101011000000100100 j
b111011100101011000000100100 !
b111011100101011000000100100 >
b10100010010011011101001100 y
b10100010010011011101001100 ?
b10100010010011011101001100 i
b10100010010011011101001100 w
b111011100101011000000100100 ;
b111011100101011000000100100 X
b111011100101011000000100100 }
b10000001 F
b10000001 V
b10000001 s
b10100010010011011101001100 h
b111011100101011000000100100 )"
b111011100101011000000100100 {
0#"
b10000001 J
b10000001 U
b10000001 \
b10000000 =
b10000000 a
b10000000 u
b10000001 I
b10000001 M
b10000001 Z
b101000100100110111010011 G
b101000100100110111010011 S
b101000100100110111010011 e
b100111010010111100011011000 x
b100111010010111100011011000 H
b100111010010111100011011000 P
b100111010010111100011011000 v
b11 q
b10000000 n
b10000000 L
b100111010010111100011011 O
b100111010010111100011011 R
b101000100100110111010011 N
b101000100100110111010011 Q
1%
b100000001 *
b100000001 8
b100000001 t
b100000001 2
b100000001 :
b100000001 k
0-
1,
1+
b1000000000111010010111100011011 (
b1000000000111010010111100011011 6
b111111101000100100110111010011 '
b111111101000100100110111010011 5
#60
0%
#70
b1000000011011100101011000000100 #
b1000000011011100101011000000100 C
b111011100101011000000100100 W
b11011100101011000000100100 "
b11011100101011000000100100 7
b11011100101011000000100100 A
b11011100101011000000100100 d
bx00 $"
bx00 -"
1%
#80
0%
#90
1%
#100
0%
#110
1%
#120
0%
#130
1%
#140
0%
#150
b10011000000100000110001100 E
b10011000000100000110001100 Y
b10011000000100000110001100 j
b10011000000100000110001100 !
b10011000000100000110001100 >
b10011000000100000110001100 ;
b10011000000100000110001100 X
b10011000000100000110001100 }
b10011000000100000110001100 )"
b10011000000100000110001100 {
b110000001000001100011000 b
1#"
b1010100010010011011101001100 y
b1010100010010011011101001100 ?
b1010100010010011011101001100 i
b1010100010010011011101001100 w
b1010100010010011011101001100 h
b110000001000001100011000 `
b1111111 =
b1111111 a
b1111111 u
b1100000010000011000110000 @
b1100000010000011000110000 l
b1101000100100110111010011 G
b1101000100100110111010011 S
b1101000100100110111010011 e
b1101000100100110111010011 N
b1101000100100110111010011 Q
1%
b100000010 *
b100000010 8
b100000010 t
b100000010 2
b100000010 :
b100000010 k
b10111111101000100100110111010011 '
b10111111101000100100110111010011 5
#160
0%
#170
b111111100110000001000001100011 #
b111111100110000001000001100011 C
b1111111 B
b1111111 T
b1111111 c
b100110000001000001100011000 W
b110000001000001100011000 "
b110000001000001100011000 7
b110000001000001100011000 A
b110000001000001100011000 d
1%
#180
0%
#190
1%
#200
0%
#210
1%
#220
0%
#230
1%
#240
0%
#250
0#"
b101010101011100001010001111 E
b101010101011100001010001111 Y
b101010101011100001010001111 j
b101010101011100001010001111 !
b101010101011100001010001111 >
b101010101011100001010001111 ;
b101010101011100001010001111 X
b101010101011100001010001111 }
b1010101011100001010010000 b
b101010101011100001010001111 )"
b101010101011100001010001111 {
bx %"
bx ,"
b10000100 F
b10000100 V
b10000100 s
b1010101011100001010001111 `
b1010101110000101000111 y
b1010101110000101000111 ?
b1010101110000101000111 i
b1010101110000101000111 w
b10000100 J
b10000100 U
b10000100 \
b101 <
b101 ]
b101 ^
b101 r
b10000011 =
b10000011 a
b10000011 u
b10101010111000010100011110 @
b10101010111000010100011110 l
b1010101110000101000111 h
b10000100 I
b10000100 M
b10000100 Z
b101001010101110000101001000 x
b101001010101110000101001000 H
b101001010101110000101001000 P
b101001010101110000101001000 v
b101 p
b101010111000010100011111 G
b101010111000010100011111 S
b101010111000010100011111 e
b1111110 n
b1111110 L
b101010111000010100011111 O
b101010111000010100011111 R
b101 q
b10000011 m
b10000011 K
b101001010101110000101001 N
b101001010101110000101001 Q
1%
10
b100000001 *
b100000001 8
b100000001 t
b100000001 2
b100000001 :
b100000001 k
b101 1
b101 9
b101 g
1-
0,
0+
b111111001010111000010100011111 (
b111111001010111000010100011111 6
b1000001101001010101110000101001 '
b1000001101001010101110000101001 5
#260
0%
#270
b1000001101010101011100001010010 #
b1000001101010101011100001010010 C
b10000011 B
b10000011 T
b10000011 c
b101010101011100001010010000 W
b1010101011100001010010000 "
b1010101011100001010010000 7
b1010101011100001010010000 A
b1010101011100001010010000 d
b101 $
b101 3
b101 D
b101 _
bx $"
bx -"
1%
#280
0%
#290
1%
#300
0%
#310
1%
#320
0%
#330
1%
#340
0%
#350
1%
