floatingpoint-COMBINED/fd.v
module fd(clock,start, operando_a, op, reset, operando_b, sinalMuxFP1, sinalMuxFP2, sinalMuxFP3, sinalMuxFP4, sinalMuxFP5, sinalShiftFract, sinalShiftRes, sinalIncOrDec, sinalRound, exp_dif, ula, round_fract, resultado);

input [31:0] operando_a, operando_b;
input sinalMuxFP1, sinalMuxFP2, sinalMuxFP3, sinalMuxFP4, sinalMuxFP5;
input [7:0] sinalShiftFract;
input [8:0] sinalShiftRes;
input clock;
input start;
input [1:0] op;
input [8:0] sinalIncOrDec;
input sinalRound;
output [31:0] resultado;
output [7:0] exp_dif;
output [26:0] ula;
input reset;
output [25:0] round_fract;


wire [7:0] ula_exp_out;
wire [7:0] reg_exp_out;
wire [7:0] mux1_out;
wire [27:0] mux2_out;
wire [24:0] mux3_out;
wire [27:0] shift_right_out;
wire [27:0] ula_out;
wire [25:0] round_fract_out;
wire [7:0] round_exp_out;
wire [7:0] mux4_out;
wire [27:0] mux5_out;
wire [7:0] ula_exp_one_out;
wire [27:0] shift_res_out;
wire [7:0] exp_op;

assign exp_dif = reg_exp_out; // Saida do registrador da diferença de expoente
assign ula = ula_out; // Saida da ula
assign round_fract = round_fract_out;
assign resultado = {shift_res_out[27], round_exp_out, round_fract_out[25:3]};

ULA_exp ula_exp(
    .a(operando_a[30:23]),
    .b(operando_b[30:23]),
    .exp_final(ula_exp_out),
    .op(op)
);

registrador registrador(
    .data_in(ula_exp_out),
    .data_out(reg_exp_out),
    .clock(clock)
);


MuxFP1 mux_fp1(
    .exp1(operando_a[30:23]),
    .exp2(operando_b[30:23]),
    .sinalMuxFP1(sinalMuxFP1), // dont care para a mult
    .greatestExp(mux1_out)
);

MuxFP2 mux_fp2(
    .fraction1({operando_a[31], 1'b1, operando_a[22:0]}),
    .fraction2({operando_b[31], 1'b1, operando_b[22:0]}), // dont care para mult
    .sinalMuxFP2(sinalMuxFP2),
    .biggerNumber(mux2_out)
);

MuxFP3 mux_fp3(
    .fraction1({operando_a[31], 1'b1, operando_a[22:0]}),
    .fraction2({operando_b[31], 1'b1, operando_b[22:0]}), // dont care para mult
    .sinalMuxFP3(sinalMuxFP3),
    .smallerNumber(mux3_out)
);

shift_fraction shift_fraction(
    .b(mux3_out),
    .sinal(sinalShiftFract),
    .op(op), // nao faz nada na mult
    .b_out(shift_right_out)
);

ULA_Float ula_float(
    .b(shift_right_out), 
    .a(mux2_out), 
    .resultado(ula_out), 
    .reset(reset), 
    .clock(clock), 
    .op(op),
    .start(start)
    );

MuxFP5 mux_fp5 (
    .fraction1(ula_out),
    .fraction2({shift_res_out[27], 1'b1, round_fract}),
    .sinalMuxFP5(sinalMuxFP5),
    .fraction(mux5_out)
);

MuxFP4 mux_fp4 (
    .exp1(exp_op),
    .exp2(round_exp_out),
    .sinalMuxFP4(sinalMuxFP4),
    .exp(mux4_out)

);

ULA_exp_one ula_exp_one (
    .b(mux4_out),
    .sinal(sinalIncOrDec),
    .res(ula_exp_one_out)

);

shift_res shift_res (
    .b(mux5_out),
    .sinal(sinalShiftRes),
    .res(shift_res_out)
);

MuxFP6 mux_fp6(
    .exp_soma(mux1_out),
    .exp_mult(ula_exp_out),
    .op(op),
    .exp_op(exp_op)
);

round round (
    .exp_inicial(ula_exp_one_out),
    .fract_inicial(shift_res_out[26:1]),
    .clock(clock),
    .sinal(sinalRound),
    .exp_final(round_exp_out),
    .fract_final(round_fract_out)
);


endmodule

module round(exp_inicial, fract_inicial, exp_final, fract_final, sinal, clock);

input clock;
input [7:0] exp_inicial;
output reg [7:0] exp_final;
input [25:0] fract_inicial;
output reg [25:0] fract_final;
wire [25:0] arredondado;
input sinal;
wire overflow;

assign {overflow,arredondado} = (fract_inicial[2:0] == 3'b111) ? ({fract_inicial[25:3]+1'b1, 3'b000}):
                           (fract_inicial[2:0] == 3'b101) ? ({fract_inicial[25:3]+1'b1, 3'b000}):
                           (fract_inicial[2:0] == 3'b110) ? ({fract_inicial[25:3]+1'b1, 3'b000}):
                           (fract_inicial[2:0] == 3'b100 && fract_inicial[3]==1'b1) ? ({fract_inicial[25:3]+1'b1, 3'b000}):
                            {fract_inicial[25:3], 3'b000};

always @(posedge clock)
begin   
    if(sinal) begin
        fract_final <= arredondado; 
    end
    else begin
        fract_final <= fract_inicial;
    end
    exp_final <= exp_inicial;

end
                           
endmodule

module registrador(clock, data_in, data_out);

input             clock;
input      [7:0] data_in;
output  reg   [7:0] data_out;


always @(posedge clock)
begin
        data_out <= data_in[7:0]; 

end

endmodule

module ULA_exp (b, a, op, exp_final);

input [7:0] b, a; 
input [1:0] op;
wire [7:0] sub;
wire [7:0] soma_exp;
output [7:0] exp_final;

assign sub = (a>b) ? (a - b): (b - a);
assign soma_exp = (a-127) + (b-127) + 2'b10; 
assign exp_final  = (op == 2'b00) ? sub: soma_exp;
     
endmodule

module shift_fraction(b, sinal, b_out, op);

input [24:0] b;
input [1:0] op;
input [7:0] sinal; //quanto shiftar
wire [27:0] res;
output [27:0] b_out;

assign res = (sinal[7:0] == 0) ? {b[24], b[23:0] >> sinal[7:0], 3'b000}:
             (sinal[7:0] == 1) ? {b[24], b[23:0] >> sinal[7:0], b[sinal-1], 2'b00}:
             (sinal[7:0] == 2) ? {b[24], b[23:0] >> sinal[7:0], b[sinal-1], b[sinal-2], 1'b0}:
             {b[24], b[23:0] >> sinal[7:0], b[sinal-1], b[sinal-2], b[sinal-3]};
assign b_out = (op == 2'b00) ? res: {b,3'b000};


endmodule

module shift_res(b, sinal, res);

input [27:0] b;
input [8:0] sinal;  
output [27:0] res;

assign res = (sinal[8] == 1)? {b[27], b[26:0] << sinal[7:0]}:
                            {b[27], b[26:0] >> sinal[7:0]};

endmodule

module ULA_exp_one (b, sinal, res);

input [7:0] b; 
input [8:0] sinal;
output [7:0] res;

assign res = (sinal[8] == 1'b0) ? (b+sinal[7:0]+127):
                                  (b-sinal[7:0]+127); 
     
endmodule

module MuxFP1 (exp1, exp2, sinalMuxFP1, greatestExp);

input [7:0] exp1;
input [7:0] exp2;
output [7:0] greatestExp; // Vai para MuxFP6
input sinalMuxFP1;

assign greatestExp = (sinalMuxFP1 == 1'b0) ? (exp1 + 1'b1) : (exp2 + 1'b1); // adicionando um bit ao expoente pois colocamos o 1 implicito para fazer as contas

endmodule

module MuxFP6 (exp_soma, exp_mult, op, exp_op);

input [7:0] exp_soma;
input [7:0] exp_mult;
output [7:0] exp_op; // Vai para MuxFP4
input [1:0] op;

assign exp_op = (op == 2'b00) ? (exp_soma) : exp_mult;

endmodule

module MuxFP2 (fraction1, fraction2, sinalMuxFP2, biggerNumber);

input [24:0] fraction1;
input [24:0] fraction2;
output [27:0] biggerNumber; // Vai receber shift para a direita e ir pra ULA grande
input sinalMuxFP2;

assign biggerNumber = (sinalMuxFP2 == 1'b0) ? {(fraction1),3'b000}  : {(fraction2), 3'b000};

endmodule

module MuxFP3 (fraction1, fraction2, sinalMuxFP3, smallerNumber);

input [24:0] fraction1;
input [24:0] fraction2;
output [24:0] smallerNumber; // Vai para ULA grande
input sinalMuxFP3;

assign smallerNumber = (sinalMuxFP3 == 1'b0) ? (fraction1) : (fraction2);

endmodule

module MuxFP4 (exp1, exp2, sinalMuxFP4, exp);

input [7:0] exp1;
input [7:0] exp2;
output [7:0] exp; // Será incrementado ou decrementado
input sinalMuxFP4;

assign exp = (sinalMuxFP4 == 1'b0) ? (exp1) : (exp2);

endmodule

module MuxFP5 (fraction1, fraction2, sinalMuxFP5, fraction);

input [27:0] fraction1;
input [27:0] fraction2;
output [27:0] fraction; // receberá shift para a direita ou esquerda
input sinalMuxFP5;

assign fraction = (sinalMuxFP5 == 1'b0) ? (fraction1) : (fraction2);

endmodule


// MULT

module ULA_Float(a, b, resultado, reset, clock, op, start); // Multiplicação

input [27:0] b, a; // Mantissa e o bit de sinal
input [1:0] op; // 00 - SOMA, 01 - MULT
wire [26:0] soma; 
wire overflow;
wire sinal;
wire [27:0] add;
input start;

assign {sinal, overflow, soma} = (a[27]|b[27] == 1'b0) ? {1'b0,(a+b)} : // OR com os bits de sinal para verificar se os dois são positivos
              (a[27] == 1'b1 && (a[26:0] > b[26:0])) ? {1'b1,(a-b)}:
              (b[27] == 1'b1 && (b[26:0] > a[26:0])) ? {1'b1,(b-a)}:
              (a[27] == 1'b1 && (a[26:0] < b[26:0])) ? {1'b0,(b-a)}:
              (b[27] == 1'b1 && (b[26:0] < a[26:0])) ? {1'b0,(a-b)}:
              {1'b0, (a+b)};

assign add = {sinal, soma};

wire [27:0] multiplicador;
wire [27:0] multiplicando;
input reset;
input clock;
wire [52:0] produto;
output [27:0] resultado;

wire [52:0] produto_in;
wire [52:0] produto_out;
wire [52:0] produto_soma;
wire [26:0] multiplicador_shift_in;
wire [26:0] multiplicador_shift_out;
wire [52:0] multiplicando_shift_in;
wire [52:0] multiplicando_shift_out;
wire [52:0] produto_shift;
wire [4:0] N_out;
wire [4:0] N_in;
wire done;

registrador_soma regA (
    .reset(reset),
    .clock(clock),
    .data_in(produto_soma),
    .data_out(produto_out)
);

registrador_N reg_N (
    .reset(reset),
    .clock(clock),
    .data_out(N_out),
    .data_in(N_in),
    .done(done)
);

subtracao sub(
    .N(N_out),
    .reset(reset),
    .sub(N_in)
);

registrador_multiplicador multR(
    .data_in(multiplicador_shift_in),
    .data_out(multiplicador_shift_out),
    .clock(clock),
    .reset(reset)
);

registrador_multiplicando multD(
    .data_in(multiplicando_shift_in),
    .data_out(multiplicando_shift_out),
    .clock(clock),
    .reset(reset)
);

assign multiplicador = a;
assign multiplicando = b;
// assign multiplicador_shift_in = multiplicador;
// assign multiplicando_shift_in = multiplicando;
assign multiplicador_shift_in = (start) ? multiplicador[26:0]: multiplicador_shift_out; //Shift do multiplicador
assign multiplicando_shift_in = (start) ? {27'b0, multiplicando[26:0]}: multiplicando_shift_out; // Shift do multiplicando
assign produto_soma = (multiplicador_shift_out[0] == 1) ? (produto_out + multiplicando_shift_out): produto_out; // Soma
assign produto = (done) ? produto_soma: 9'bz; // Produto final

assign resultado = (op == 2'b00) ? add: {a[27]^b[27],produto[52:26]};

endmodule

module registrador_multiplicador(data_in, data_out, clock, reset);

input             clock;
input      [26:0] data_in;
input               reset;
output  reg   [26:0] data_out;

always @(posedge clock or posedge reset)
begin   
        if(reset) begin
            data_out <= data_in;
        end else begin
            data_out <= data_in >> 1; 
        end

end
endmodule

module registrador_multiplicando(data_in, data_out, clock, reset);

input             clock;
input      [52:0] data_in;
input               reset;
output  reg   [52:0] data_out;

always @(posedge clock or posedge reset)
begin   

        if(reset) begin
            data_out <= data_in;
        end else begin
            data_out <= data_in << 1; 
        end 

end
endmodule

module registrador_soma(clock, data_in, data_out, reset);

input             clock;
input      [52:0] data_in;
input               reset;
output  reg   [52:0] data_out;

always @(posedge clock or posedge reset)
begin   
        if(reset) 
            data_out <= 0;
        else 
            data_out <= data_in[54:0]; 

end
endmodule

module subtracao(N, sub, reset);

input [4:0]  N;
input reset;
output [4:0] sub;

assign sub = (~reset) ? N - 1 : N;

endmodule

module registrador_N(clock, data_out, data_in, reset, done);

input             clock;
input               reset;
output  reg   [4:0] data_out;
input           [4:0] data_in;
output   reg          done;

always @(posedge clock or posedge reset)
begin   
        if(reset) begin
            done <=0;
            data_out <= 5'b11011;
        end
        else 
            data_out <= data_in[4:0]; 
            if(data_in == 0)
                done <= 1;

end
endmodule

floatingpoint-COMBINED/tb.v
// **********GRUPO ************
// Helena Bianchi Moyen
// Luiz Mariano
// Mariana Watanabe


`timescale 1ns/1ns

module testbench;

    reg [31:0] operando_a_tb, operando_b_tb;
    reg sinalMuxFP1_tb, sinalMuxFP2_tb, sinalMuxFP3_tb, sinalMuxFP4_tb, sinalMuxFP5_tb;
    reg [7:0] sinalShiftFract_tb;
    reg [8:0] sinalShiftRes_tb;
    reg [8:0] sinalIncOrDec_tb;
    reg sinalRound_tb;
    reg clock_tb;
    reg start_tb;
    reg [1:0] op_tb;
    reg reset_tb;

    wire [31:0] resultado_tb;
    wire [7:0] exp_dif_tb;
    wire [26:0] ula_tb;
    wire [25:0] round_fract_tb;

    fd fd(
        .clock(clock_tb), 
        .op(op_tb),
        .start(start_tb),
        .operando_a(operando_a_tb), 
        .operando_b(operando_b_tb),
        .sinalMuxFP1(sinalMuxFP1_tb), 
        .sinalMuxFP2(sinalMuxFP2_tb), 
        .sinalMuxFP4(sinalMuxFP4_tb),
        .sinalMuxFP3(sinalMuxFP3_tb), 
        .sinalMuxFP5(sinalMuxFP5_tb), 
        .sinalShiftFract(sinalShiftFract_tb), 
        .sinalShiftRes(sinalShiftRes_tb), 
        .sinalIncOrDec(sinalIncOrDec_tb), 
        .sinalRound(sinalRound_tb), 
        .exp_dif(exp_dif_tb), 
        .ula(ula_tb), 
        .reset(reset_tb),
        .round_fract(round_fract_tb), 
        .resultado(resultado_tb)
    );

    initial $dumpfile("testbench.vcd");
    initial $dumpvars(0, testbench);

    initial 
    begin
        
        //*******************************Abaixo é a simulação: ********************************************************************
        clock_tb =0;
        op_tb = 2'b00;
        operando_a_tb = 32'b00111111110000000000000000000000; // 1,5
        operando_b_tb = 32'b00111111000000000000000000000000; // 0,5
        sinalMuxFP1_tb = 0; // exp de 0,5 eh menor que de 1,5
        sinalMuxFP2_tb = 0; // a > b
        sinalMuxFP3_tb = 1; // b < a
        sinalMuxFP5_tb = 0;
        sinalShiftFract_tb = 1; // shift de b em 1
        sinalShiftRes_tb  = 9'b100000000; // nao precisamos shiftar nada (mantissa eh 0)
        sinalIncOrDec_tb  = 9'b000000000; // 
        sinalMuxFP4_tb = 0;
        sinalRound_tb = 0;
        // esperado: 01000000000000000000000000000000 =
        #50
        $display("Resultado de 1,5 + 0,5: %b", resultado_tb);
        op_tb = 2'b00;
        operando_a_tb = 32'b00111111101000100100110111010011; // 1,268
        operando_b_tb = 32'b01000000000111010010111100011011; // 2,456
        // esperado : 01000000011011100101011000000100 = 3,724
        sinalMuxFP1_tb = 1; // exp de 1,268 eh menor que de 2,456
        sinalMuxFP2_tb = 1; // b > a (em modulo)
        sinalMuxFP3_tb = 0; // a < b (eme modulo)
        sinalMuxFP5_tb = 0;
        sinalShiftFract_tb = 1; // shift de a em 1
        sinalShiftRes_tb  = 9'b100000001; // shift de um para esquerda 
        sinalIncOrDec_tb  = 9'b100000001; // decrementa 1, pois shiftamos uma vez para a esquerda
        sinalMuxFP4_tb = 0;
        sinalRound_tb = 0;
        #100
        $display("Resultado de 1,268 + 2,456 %b", resultado_tb);
        op_tb = 2'b00;
        operando_a_tb = 32'b10111111101000100100110111010011; // -1,268
        operando_b_tb = 32'b01000000000111010010111100011011; // 2,456
        // esperado : 00111111100110000001000001100011 = 1,188000
         //           00111111100110000001000001100011
        sinalMuxFP1_tb = 1; // exp de 1,268 eh menor que de 2,456
        sinalMuxFP2_tb = 1; // b > a (em modulo)
        sinalMuxFP3_tb = 0; // a < b (em modulo)
        sinalMuxFP5_tb = 0;
        sinalShiftFract_tb = 1; // shift de a em 1
        sinalShiftRes_tb  = 9'b100000010; // shift de dois para esquerda 
        sinalIncOrDec_tb  = 9'b100000010; // decrementa 2, pois shiftamos duas vezes para a esquerda
        sinalMuxFP4_tb = 0;
        sinalRound_tb = 0;
        #100
        $display("Resultado de - 1,268 + 2,456 %b", resultado_tb);
        op_tb = 2'b00;
        operando_a_tb = 32'b01000001101001010101110000101001; // 20.6700000763
        operando_b_tb = 32'b00111111001010111000010100011111; // 0.670000016689
        // esperado : 01000001101010101011100001010010 = 21.3400001526
        sinalMuxFP1_tb = 0; // exp de 0.67 eh menor 
        sinalMuxFP2_tb = 0; // a > b
        sinalMuxFP3_tb = 1; // b < a
        sinalMuxFP5_tb = 0;
        sinalShiftFract_tb = 5; 
        sinalShiftRes_tb  = 9'b100000001; // shift de dois para esquerda 
        sinalIncOrDec_tb  = 9'b100000001; // decrementa 2, pois shiftamos duas vezes para a esquerda
        sinalMuxFP4_tb = 0;
        sinalRound_tb = 1; // Verifique no GTK Wave o arredondamento que o corre
        #100

        $display("Resultado de 20.67 + 0.67  %b", resultado_tb);
        reset_tb = 1;
        start_tb = 1;
        op_tb = 2'b10;
        operando_a_tb = 32'b00111111101001010110000001000010; //1.292
        operando_b_tb = 32'b00111111110000000000000000000000;//1.5
        sinalMuxFP1_tb = 0; // exp de 0.67 eh menor 
        sinalMuxFP2_tb = 0; // a > b
        sinalMuxFP3_tb = 1; // b < a
        sinalMuxFP4_tb = 0; 
        sinalMuxFP5_tb = 0;
        sinalShiftRes_tb  = 9'b100000001; 
        sinalIncOrDec_tb  = 9'b100000010;
        #10
        #20
        start_tb = 0;
        reset_tb = 0;
        #1000
        $display("Fim da simulação: %b", resultado_tb);
        $finish;

        $display("Fim da simulação");
        $finish;

     
    end

        always #10 clock_tb = ~clock_tb;
    
    

endmodule

floatingpoint-COMBINED/testbench.vcd
$date
	Thu Jun 29 19:18:42 2023
$end
$version
	Icarus Verilog
$end
$timescale
	1ns
$end
$scope module testbench $end
$var wire 27 ! ula_tb [26:0] $end
$var wire 26 " round_fract_tb [25:0] $end
$var wire 32 # resultado_tb [31:0] $end
$var wire 8 $ exp_dif_tb [7:0] $end
$var reg 1 % clock_tb $end
$var reg 2 & op_tb [1:0] $end
$var reg 32 ' operando_a_tb [31:0] $end
$var reg 32 ( operando_b_tb [31:0] $end
$var reg 1 ) reset_tb $end
$var reg 9 * sinalIncOrDec_tb [8:0] $end
$var reg 1 + sinalMuxFP1_tb $end
$var reg 1 , sinalMuxFP2_tb $end
$var reg 1 - sinalMuxFP3_tb $end
$var reg 1 . sinalMuxFP4_tb $end
$var reg 1 / sinalMuxFP5_tb $end
$var reg 1 0 sinalRound_tb $end
$var reg 8 1 sinalShiftFract_tb [7:0] $end
$var reg 9 2 sinalShiftRes_tb [8:0] $end
$var reg 1 3 start_tb $end
$scope module fd $end
$var wire 1 % clock $end
$var wire 8 4 exp_dif [7:0] $end
$var wire 2 5 op [1:0] $end
$var wire 32 6 operando_a [31:0] $end
$var wire 32 7 operando_b [31:0] $end
$var wire 1 ) reset $end
$var wire 26 8 round_fract [25:0] $end
$var wire 9 9 sinalIncOrDec [8:0] $end
$var wire 1 + sinalMuxFP1 $end
$var wire 1 , sinalMuxFP2 $end
$var wire 1 - sinalMuxFP3 $end
$var wire 1 . sinalMuxFP4 $end
$var wire 1 / sinalMuxFP5 $end
$var wire 1 0 sinalRound $end
$var wire 8 : sinalShiftFract [7:0] $end
$var wire 9 ; sinalShiftRes [8:0] $end
$var wire 1 3 start $end
$var wire 28 < ula_out [27:0] $end
$var wire 8 = ula_exp_out [7:0] $end
$var wire 8 > ula_exp_one_out [7:0] $end
$var wire 27 ? ula [26:0] $end
$var wire 28 @ shift_right_out [27:0] $end
$var wire 28 A shift_res_out [27:0] $end
$var wire 26 B round_fract_out [25:0] $end
$var wire 8 C round_exp_out [7:0] $end
$var wire 32 D resultado [31:0] $end
$var wire 8 E reg_exp_out [7:0] $end
$var wire 28 F mux5_out [27:0] $end
$var wire 8 G mux4_out [7:0] $end
$var wire 25 H mux3_out [24:0] $end
$var wire 28 I mux2_out [27:0] $end
$var wire 8 J mux1_out [7:0] $end
$var wire 8 K exp_op [7:0] $end
$scope module mux_fp1 $end
$var wire 8 L exp1 [7:0] $end
$var wire 8 M exp2 [7:0] $end
$var wire 1 + sinalMuxFP1 $end
$var wire 8 N greatestExp [7:0] $end
$upscope $end
$scope module mux_fp2 $end
$var wire 25 O fraction1 [24:0] $end
$var wire 25 P fraction2 [24:0] $end
$var wire 1 , sinalMuxFP2 $end
$var wire 28 Q biggerNumber [27:0] $end
$upscope $end
$scope module mux_fp3 $end
$var wire 25 R fraction1 [24:0] $end
$var wire 25 S fraction2 [24:0] $end
$var wire 1 - sinalMuxFP3 $end
$var wire 25 T smallerNumber [24:0] $end
$upscope $end
$scope module mux_fp4 $end
$var wire 1 . sinalMuxFP4 $end
$var wire 8 U exp2 [7:0] $end
$var wire 8 V exp1 [7:0] $end
$var wire 8 W exp [7:0] $end
$upscope $end
$scope module mux_fp5 $end
$var wire 28 X fraction2 [27:0] $end
$var wire 1 / sinalMuxFP5 $end
$var wire 28 Y fraction1 [27:0] $end
$var wire 28 Z fraction [27:0] $end
$upscope $end
$scope module mux_fp6 $end
$var wire 8 [ exp_soma [7:0] $end
$var wire 2 \ op [1:0] $end
$var wire 8 ] exp_op [7:0] $end
$var wire 8 ^ exp_mult [7:0] $end
$upscope $end
$scope module registrador $end
$var wire 1 % clock $end
$var wire 8 _ data_in [7:0] $end
$var reg 8 ` data_out [7:0] $end
$upscope $end
$scope module round $end
$var wire 1 % clock $end
$var wire 26 a fract_inicial [25:0] $end
$var wire 1 0 sinal $end
$var wire 1 b overflow $end
$var wire 8 c exp_inicial [7:0] $end
$var wire 26 d arredondado [25:0] $end
$var reg 8 e exp_final [7:0] $end
$var reg 26 f fract_final [25:0] $end
$upscope $end
$scope module shift_fraction $end
$var wire 25 g b [24:0] $end
$var wire 2 h op [1:0] $end
$var wire 8 i sinal [7:0] $end
$var wire 28 j res [27:0] $end
$var wire 28 k b_out [27:0] $end
$upscope $end
$scope module shift_res $end
$var wire 28 l b [27:0] $end
$var wire 9 m sinal [8:0] $end
$var wire 28 n res [27:0] $end
$upscope $end
$scope module ula_exp $end
$var wire 8 o a [7:0] $end
$var wire 8 p b [7:0] $end
$var wire 2 q op [1:0] $end
$var wire 8 r sub [7:0] $end
$var wire 8 s soma_exp [7:0] $end
$var wire 8 t exp_final [7:0] $end
$upscope $end
$scope module ula_exp_one $end
$var wire 8 u b [7:0] $end
$var wire 9 v sinal [8:0] $end
$var wire 8 w res [7:0] $end
$upscope $end
$scope module ula_float $end
$var wire 28 x a [27:0] $end
$var wire 28 y b [27:0] $end
$var wire 1 % clock $end
$var wire 28 z multiplicador [27:0] $end
$var wire 28 { multiplicando [27:0] $end
$var wire 2 | op [1:0] $end
$var wire 1 ) reset $end
$var wire 1 3 start $end
$var wire 27 } soma [26:0] $end
$var wire 1 ~ sinal $end
$var wire 28 !" resultado [27:0] $end
$var wire 53 "" produto_soma [52:0] $end
$var wire 53 #" produto_out [52:0] $end
$var wire 53 $" produto [52:0] $end
$var wire 1 %" overflow $end
$var wire 53 &" multiplicando_shift_out [52:0] $end
$var wire 53 '" multiplicando_shift_in [52:0] $end
$var wire 27 (" multiplicador_shift_out [26:0] $end
$var wire 27 )" multiplicador_shift_in [26:0] $end
$var wire 1 *" done $end
$var wire 28 +" add [27:0] $end
$var wire 5 ," N_out [4:0] $end
$var wire 5 -" N_in [4:0] $end
$scope module multD $end
$var wire 1 % clock $end
$var wire 53 ." data_in [52:0] $end
$var wire 1 ) reset $end
$var reg 53 /" data_out [52:0] $end
$upscope $end
$scope module multR $end
$var wire 1 % clock $end
$var wire 27 0" data_in [26:0] $end
$var wire 1 ) reset $end
$var reg 27 1" data_out [26:0] $end
$upscope $end
$scope module regA $end
$var wire 1 % clock $end
$var wire 53 2" data_in [52:0] $end
$var wire 1 ) reset $end
$var reg 53 3" data_out [52:0] $end
$upscope $end
$scope module reg_N $end
$var wire 1 % clock $end
$var wire 1 ) reset $end
$var wire 5 4" data_in [4:0] $end
$var reg 5 5" data_out [4:0] $end
$var reg 1 *" done $end
$upscope $end
$scope module sub $end
$var wire 5 6" N [4:0] $end
$var wire 1 ) reset $end
$var wire 5 7" sub [4:0] $end
$upscope $end
$upscope $end
$upscope $end
$upscope $end
$enddefinitions $end
#0
$dumpvars
bx 7"
bx 6"
bx 5"
bx 4"
bx 3"
bx 2"
bx 1"
bx 0"
bx /"
bx ."
bx -"
bx ,"
b0 +"
x*"
bx )"
bx ("
bx '"
bx &"
1%"
bx $"
bx #"
bx ""
b0 !"
0~
b0 }
b0 |
b10000000000000000000000000 {
b110000000000000000000000000 z
b10000000000000000000000000 y
b110000000000000000000000000 x
b11111111 w
b0 v
b10000000 u
b1 t
b1 s
b1 r
b0 q
b1111110 p
b1111111 o
b0 n
b100000000 m
b0 l
b10000000000000000000000000 k
b10000000000000000000000000 j
b1 i
b0 h
b100000000000000000000000 g
bx f
bx e
b0 d
b11111111 c
0b
b0 a
bx `
b1 _
b1 ^
b10000000 ]
b0 \
b10000000 [
b0 Z
b0 Y
b1xxxxxxxxxxxxxxxxxxxxxxxxxx X
b10000000 W
b10000000 V
bx U
b100000000000000000000000 T
b100000000000000000000000 S
b110000000000000000000000 R
b110000000000000000000000000 Q
b100000000000000000000000 P
b110000000000000000000000 O
b10000000 N
b1111110 M
b1111111 L
b10000000 K
b10000000 J
b110000000000000000000000000 I
b100000000000000000000000 H
b10000000 G
b0 F
bx E
b0xxxxxxxxxxxxxxxxxxxxxxxxxxxxxxx D
bx C
bx B
b0 A
b10000000000000000000000000 @
b0 ?
b11111111 >
b1 =
b0 <
b100000000 ;
b1 :
b0 9
bx 8
b111111000000000000000000000000 7
b111111110000000000000000000000 6
b0 5
bx 4
x3
b100000000 2
b1 1
00
0/
0.
1-
0,
0+
b0 *
x)
b111111000000000000000000000000 (
b111111110000000000000000000000 '
b0 &
0%
bx $
b0xxxxxxxxxxxxxxxxxxxxxxxxxxxxxxx #
bx "
b0 !
$end
#10
bx0 '"
bx0 ."
b1 $
b1 4
b1 E
b1 `
b1111111100000000000000000000000 #
b1111111100000000000000000000000 D
b11111111 C
b11111111 U
b11111111 e
b100000000000000000000000000 X
b0 "
b0 8
b0 B
b0 f
b0xxxxxxxxxxxxxxxxxxxxxxxxxx ("
b0xxxxxxxxxxxxxxxxxxxxxxxxxx 1"
bx0 &"
bx0 /"
1%
#20
0%
#30
bx00 '"
bx00 ."
bx00 &"
bx00 /"
1%
#40
0%
#50
bx000 &"
bx000 /"
b11011100101011000000100000 d
b11011100101011000000100100 a
b110111001010110000001001000 A
b110111001010110000001001000 n
b111011100101011000000100100 F
b111011100101011000000100100 Z
b111011100101011000000100100 l
b111011100101011000000100100 !
b111011100101011000000100100 ?
b10100010010011011101001100 {
b10100010010011011101001100 @
b10100010010011011101001100 k
b10100010010011011101001100 y
b111011100101011000000100100 <
b111011100101011000000100100 Y
b111011100101011000000100100 !"
b10000001 G
b10000001 W
b10000001 u
b10100010010011011101001100 j
b111011100101011000000100100 +"
b111011100101011000000100100 }
0%"
b10000001 K
b10000001 V
b10000001 ]
b11111111 >
b11111111 c
b11111111 w
b10000001 J
b10000001 N
b10000001 [
b101000100100110111010011 H
b101000100100110111010011 T
b101000100100110111010011 g
b100111010010111100011011000 z
b100111010010111100011011000 I
b100111010010111100011011000 Q
b100111010010111100011011000 x
b11 s
b10000000 p
b10000000 M
b100111010010111100011011 P
b100111010010111100011011 S
b101000100100110111010011 O
b101000100100110111010011 R
1%
b100000001 *
b100000001 9
b100000001 v
b100000001 2
b100000001 ;
b100000001 m
0-
1,
1+
b1000000000111010010111100011011 (
b1000000000111010010111100011011 7
b111111101000100100110111010011 '
b111111101000100100110111010011 6
#60
0%
#70
b1111111111011100101011000000100 #
b1111111111011100101011000000100 D
b111011100101011000000100100 X
b11011100101011000000100100 "
b11011100101011000000100100 8
b11011100101011000000100100 B
b11011100101011000000100100 f
1%
#80
0%
#90
1%
#100
0%
#110
1%
#120
0%
#130
1%
#140
0%
#150
b10011000000100000110001100 F
b10011000000100000110001100 Z
b10011000000100000110001100 l
b10011000000100000110001100 !
b10011000000100000110001100 ?
b10011000000100000110001100 <
b10011000000100000110001100 Y
b10011000000100000110001100 !"
b10011000000100000110001100 +"
b10011000000100000110001100 }
b110000001000001100011000 d
1%"
b1010100010010011011101001100 {
b1010100010010011011101001100 @
b1010100010010011011101001100 k
b1010100010010011011101001100 y
b1010100010010011011101001100 j
b110000001000001100011000 a
b11111110 >
b11111110 c
b11111110 w
b1100000010000011000110000 A
b1100000010000011000110000 n
b1101000100100110111010011 H
b1101000100100110111010011 T
b1101000100100110111010011 g
b1101000100100110111010011 O
b1101000100100110111010011 R
1%
b100000010 *
b100000010 9
b100000010 v
b100000010 2
b100000010 ;
b100000010 m
b10111111101000100100110111010011 '
b10111111101000100100110111010011 6
#160
0%
#170
b1111111000110000001000001100011 #
b1111111000110000001000001100011 D
b11111110 C
b11111110 U
b11111110 e
b100110000001000001100011000 X
b110000001000001100011000 "
b110000001000001100011000 8
b110000001000001100011000 B
b110000001000001100011000 f
1%
#180
0%
#190
1%
#200
0%
#210
1%
#220
0%
#230
1%
#240
0%
#250
0%"
b101010101011100001010001111 F
b101010101011100001010001111 Z
b101010101011100001010001111 l
b101010101011100001010001111 !
b101010101011100001010001111 ?
b1010101011100001010010000 d
b101010101011100001010001111 <
b101010101011100001010001111 Y
b101010101011100001010001111 !"
bx '"
bx ."
b101010101011100001010001111 +"
b101010101011100001010001111 }
b10000100 G
b10000100 W
b10000100 u
b1010101011100001010001111 a
b1010101110000101000111 {
b1010101110000101000111 @
b1010101110000101000111 k
b1010101110000101000111 y
b10000100 K
b10000100 V
b10000100 ]
b101 =
b101 ^
b101 _
b101 t
b10 >
b10 c
b10 w
b10101010111000010100011110 A
b10101010111000010100011110 n
b1010101110000101000111 j
b10000100 J
b10000100 N
b10000100 [
b101001010101110000101001000 z
b101001010101110000101001000 I
b101001010101110000101001000 Q
b101001010101110000101001000 x
b101 r
b101010111000010100011111 H
b101010111000010100011111 T
b101010111000010100011111 g
b1111110 p
b1111110 M
b101010111000010100011111 P
b101010111000010100011111 S
b101 s
b10000011 o
b10000011 L
b101001010101110000101001 O
b101001010101110000101001 R
1%
10
b100000001 *
b100000001 9
b100000001 v
b100000001 2
b100000001 ;
b100000001 m
b101 1
b101 :
b101 i
1-
0,
0+
b111111001010111000010100011111 (
b111111001010111000010100011111 7
b1000001101001010101110000101001 '
b1000001101001010101110000101001 6
#260
0%
